{"dice":[1,10,11],"summary":{"solvableCount":47,"impossibleCount":952,"minDifficulty":-6.06,"maxDifficulty":99.27,"averageDifficulty":13.66},"solutions":{"1":{"difficulty":-6.06,"equation":"1^0 * 10^0 * 11^0 = 1"},"2":{"difficulty":-5.69,"equation":"1^0 + 10^0 * 11^0 = 2"},"3":{"difficulty":-4.42,"equation":"1^0 + 10^0 + 11^0 = 3"},"8":{"difficulty":-2.39,"equation":"10^1 - 1^0 - 11^0 = 8"},"9":{"difficulty":-4.26,"equation":"1^0 * 10^1 - 11^0 = 9"},"10":{"difficulty":-4.29,"equation":"1^0 * 10^1 * 11^0 = 10"},"11":{"difficulty":-4.2,"equation":"1^0 * 10^0 * 11^1 = 11"},"12":{"difficulty":-3.99,"equation":"1^0 * 10^0 + 11^1 = 12"},"13":{"difficulty":-1.61,"equation":"1^0 + 10^0 + 11^1 = 13"},"20":{"difficulty":-2.3,"equation":"1^0 + 11^0 * 10^1 = 20"},"21":{"difficulty":-1.73,"equation":"1^0 * 10^1 + 11^1 = 21"},"22":{"difficulty":-1.99,"equation":"1^0 + 10^0 * 11^1 = 22"},"88":{"difficulty":9.07,"equation":"10^2 - 1^0 - 11^1 = 88"},"89":{"difficulty":2.23,"equation":"1^0 * 10^2 - 11^1 = 89"},"90":{"difficulty":8.72,"equation":"1^0 + 10^2 - 11^1 = 90"},"91":{"difficulty":99.03,"equation":"1^0 + 10^3 / 11^1 = 91"},"98":{"difficulty":6.53,"equation":"10^2 - 1^0 - 11^0 = 98"},"99":{"difficulty":0.78,"equation":"1^0 * 10^2 - 11^0 = 99"},"100":{"difficulty":0.67,"equation":"1^0 * 10^2 * 11^0 = 100"},"101":{"difficulty":0.83,"equation":"1^0 + 10^2 * 11^0 = 101"},"102":{"difficulty":6.73,"equation":"1^0 + 10^2 + 11^0 = 102"},"109":{"difficulty":2.7,"equation":"10^1 * 11^1 - 1^0 = 109"},"110":{"difficulty":1.08,"equation":"10^1 * 11^1 * 1^0 = 110"},"111":{"difficulty":2.76,"equation":"11^2 - 10^1 * 1^0 = 111"},"112":{"difficulty":9.66,"equation":"1^0 - 10^1 + 11^2 = 112"},"119":{"difficulty":7.6,"equation":"11^2 - 1^0 - 10^0 = 119"},"120":{"difficulty":1.38,"equation":"10^0 * 11^2 - 1^0 = 120"},"121":{"difficulty":1.28,"equation":"1^0 * 10^0 * 11^2 = 121"},"122":{"difficulty":1.44,"equation":"1^0 * 10^0 + 11^2 = 122"},"123":{"difficulty":7.79,"equation":"1^0 + 10^0 + 11^2 = 123"},"130":{"difficulty":10.47,"equation":"10^1 - 1^0 + 11^2 = 130"},"131":{"difficulty":3.28,"equation":"1^0 * 10^1 + 11^2 = 131"},"132":{"difficulty":11.01,"equation":"1^0 + 10^1 + 11^2 = 132"},"200":{"difficulty":14.97,"equation":"1^0 + 11^0 * 10^2 = 200"},"220":{"difficulty":35.69,"equation":"10^2 - 1^0 + 11^2 = 220"},"221":{"difficulty":17.69,"equation":"1^0 * 10^2 + 11^2 = 221"},"222":{"difficulty":36.21,"equation":"1^0 + 10^2 + 11^2 = 222"},"242":{"difficulty":19.52,"equation":"1^0 + 10^0 * 11^2 = 242"},"878":{"difficulty":56.98,"equation":"10^3 - 1^0 - 11^2 = 878"},"879":{"difficulty":29.58,"equation":"1^0 * 10^3 - 11^2 = 879"},"880":{"difficulty":56.56,"equation":"1^0 + 10^3 - 11^2 = 880"},"909":{"difficulty":99.27,"equation":"10^4 - 1^0 / 11^1 = 909"},"988":{"difficulty":32.47,"equation":"10^3 - 1^0 - 11^1 = 988"},"989":{"difficulty":15.58,"equation":"1^0 * 10^3 - 11^1 = 989"},"990":{"difficulty":32.05,"equation":"1^0 + 10^3 - 11^1 = 990"},"998":{"difficulty":29.58,"equation":"10^3 - 1^0 - 11^0 = 998"},"999":{"difficulty":13.92,"equation":"1^0 * 10^3 - 11^0 = 999"}}}