{"dice":[10,10,19],"summary":{"solvableCount":99,"impossibleCount":900,"minDifficulty":-6.06,"maxDifficulty":99.02,"averageDifficulty":23.52},"solutions":{"1":{"difficulty":-6.06,"equation":"10^0 * 10^0 * 19^0 = 1"},"2":{"difficulty":-5.69,"equation":"10^0 + 10^0 * 19^0 = 2"},"3":{"difficulty":-4.42,"equation":"10^0 + 10^0 + 19^0 = 3"},"8":{"difficulty":-2.39,"equation":"10^1 - 10^0 - 19^0 = 8"},"9":{"difficulty":-4.26,"equation":"10^0 * 10^1 - 19^0 = 9"},"10":{"difficulty":-4.29,"equation":"10^0 * 10^1 * 19^0 = 10"},"11":{"difficulty":-4.08,"equation":"10^0 + 10^1 * 19^0 = 11"},"12":{"difficulty":-1.76,"equation":"10^0 + 10^1 + 19^0 = 12"},"17":{"difficulty":-1.03,"equation":"19^1 - 10^0 - 10^0 = 17"},"18":{"difficulty":-3.5,"equation":"10^0 * 19^1 - 10^0 = 18"},"19":{"difficulty":-3.57,"equation":"10^0 * 10^0 * 19^1 = 19"},"20":{"difficulty":-3.37,"equation":"10^0 * 10^0 + 19^1 = 20"},"21":{"difficulty":-0.57,"equation":"10^0 + 10^0 + 19^1 = 21"},"28":{"difficulty":2.52,"equation":"10^1 - 10^0 + 19^1 = 28"},"29":{"difficulty":-1.23,"equation":"10^0 * 10^1 + 19^1 = 29"},"30":{"difficulty":3.16,"equation":"10^0 + 10^1 + 19^1 = 30"},"36":{"difficulty":51.38,"equation":"19^2 - 10^0 / 10^1 = 36"},"38":{"difficulty":-0.08,"equation":"10^0 + 10^0 * 19^1 = 38"},"39":{"difficulty":6.76,"equation":"10^1 + 10^1 + 19^1 = 39"},"71":{"difficulty":12.75,"equation":"10^2 - 10^1 - 19^1 = 71"},"80":{"difficulty":10.44,"equation":"10^2 - 10^0 - 19^1 = 80"},"81":{"difficulty":3.01,"equation":"10^0 * 10^2 - 19^1 = 81"},"82":{"difficulty":10.1,"equation":"10^0 + 10^2 - 19^1 = 82"},"89":{"difficulty":8.9,"equation":"10^2 - 10^1 - 19^0 = 89"},"90":{"difficulty":2.13,"equation":"10^2 - 10^1 * 19^0 = 90"},"91":{"difficulty":8.55,"equation":"10^2 - 10^1 + 19^0 = 91"},"98":{"difficulty":6.53,"equation":"10^2 - 10^0 - 19^0 = 98"},"99":{"difficulty":0.78,"equation":"10^0 * 10^2 - 19^0 = 99"},"100":{"difficulty":0.31,"equation":"10^1 * 10^1 * 19^0 = 100"},"101":{"difficulty":0.83,"equation":"10^0 + 10^2 * 19^0 = 101"},"102":{"difficulty":6.73,"equation":"10^0 + 10^2 + 19^0 = 102"},"109":{"difficulty":9.45,"equation":"10^1 + 10^2 - 19^0 = 109"},"110":{"difficulty":2.7,"equation":"10^1 + 10^2 * 19^0 = 110"},"111":{"difficulty":10,"equation":"10^1 + 10^2 + 19^0 = 111"},"118":{"difficulty":11.91,"equation":"10^2 - 10^0 + 19^1 = 118"},"119":{"difficulty":4.1,"equation":"10^0 * 10^2 + 19^1 = 119"},"120":{"difficulty":12.45,"equation":"10^0 + 10^2 + 19^1 = 120"},"129":{"difficulty":15.69,"equation":"10^1 + 10^2 + 19^1 = 129"},"161":{"difficulty":47.53,"equation":"19^2 - 10^2 - 10^2 = 161"},"171":{"difficulty":17.66,"equation":"10^1 - 10^0 * 19^1 = 171"},"180":{"difficulty":9.09,"equation":"10^1 * 19^1 - 10^1 = 180"},"181":{"difficulty":30.97,"equation":"10^2 + 10^2 - 19^1 = 181"},"189":{"difficulty":8.51,"equation":"10^1 * 19^1 - 10^0 = 189"},"190":{"difficulty":6.89,"equation":"10^1 * 19^1 * 10^0 = 190"},"191":{"difficulty":8.65,"equation":"10^1 * 19^1 + 10^0 = 191"},"199":{"difficulty":34.9,"equation":"10^2 + 10^2 - 19^0 = 199"},"200":{"difficulty":10,"equation":"10^0 + 19^1 * 10^1 = 200"},"201":{"difficulty":35.43,"equation":"10^2 + 10^2 + 19^0 = 201"},"209":{"difficulty":11.34,"equation":"10^0 + 10^1 * 19^1 = 209"},"219":{"difficulty":40.91,"equation":"10^2 + 10^2 + 19^1 = 219"},"251":{"difficulty":40.48,"equation":"19^2 - 10^1 - 10^2 = 251"},"260":{"difficulty":37.94,"equation":"19^2 - 10^0 - 10^2 = 260"},"261":{"difficulty":18.71,"equation":"10^0 * 19^2 - 10^2 = 261"},"262":{"difficulty":37.54,"equation":"10^0 - 10^2 + 19^2 = 262"},"271":{"difficulty":36.58,"equation":"10^1 - 10^2 + 19^2 = 271"},"290":{"difficulty":18.07,"equation":"10^1 + 19^1 * 10^1 = 290"},"341":{"difficulty":21.32,"equation":"19^2 - 10^1 - 10^1 = 341"},"350":{"difficulty":18.73,"equation":"19^2 - 10^0 - 10^1 = 350"},"351":{"difficulty":7.73,"equation":"10^0 * 19^2 - 10^1 = 351"},"352":{"difficulty":18.33,"equation":"10^0 - 10^1 + 19^2 = 352"},"359":{"difficulty":16.14,"equation":"19^2 - 10^0 - 10^0 = 359"},"360":{"difficulty":6.25,"equation":"10^0 * 19^2 - 10^0 = 360"},"361":{"difficulty":6.14,"equation":"10^0 * 10^0 * 19^2 = 361"},"362":{"difficulty":6.28,"equation":"10^0 * 10^0 + 19^2 = 362"},"363":{"difficulty":16.25,"equation":"10^0 + 10^0 + 19^2 = 363"},"370":{"difficulty":18.81,"equation":"10^1 - 10^0 + 19^2 = 370"},"371":{"difficulty":8.03,"equation":"10^0 * 10^1 + 19^2 = 371"},"372":{"difficulty":19.31,"equation":"10^0 + 10^1 + 19^2 = 372"},"380":{"difficulty":24.35,"equation":"10^1 + 10^1 * 19^1 = 380"},"381":{"difficulty":22.37,"equation":"10^1 + 10^1 + 19^2 = 381"},"451":{"difficulty":41.35,"equation":"10^2 - 10^1 + 19^2 = 451"},"460":{"difficulty":42.81,"equation":"10^2 - 10^0 + 19^2 = 460"},"461":{"difficulty":21.75,"equation":"10^0 * 10^2 + 19^2 = 461"},"462":{"difficulty":43.3,"equation":"10^0 + 10^2 + 19^2 = 462"},"471":{"difficulty":46.34,"equation":"10^1 + 10^2 + 19^2 = 471"},"539":{"difficulty":99.02,"equation":"10^3 - 10^2 - 19^2 = 539"},"561":{"difficulty":70.11,"equation":"10^2 + 10^2 + 19^2 = 561"},"629":{"difficulty":99.02,"equation":"10^3 - 10^1 - 19^2 = 629"},"638":{"difficulty":99.02,"equation":"10^3 - 10^0 - 19^2 = 638"},"639":{"difficulty":54.15,"equation":"10^0 * 10^3 - 19^2 = 639"},"640":{"difficulty":99.02,"equation":"10^0 + 10^3 - 19^2 = 640"},"649":{"difficulty":99.02,"equation":"10^1 + 10^3 - 19^2 = 649"},"722":{"difficulty":53.34,"equation":"10^0 + 10^0 * 19^2 = 722"},"739":{"difficulty":88.2,"equation":"10^2 + 10^3 - 19^2 = 739"},"810":{"difficulty":73.53,"equation":"10^2 - 19^1 * 10^1 = 810"},"881":{"difficulty":57.15,"equation":"10^3 - 10^2 - 19^1 = 881"},"899":{"difficulty":52.58,"equation":"10^3 - 10^2 - 19^0 = 899"},"900":{"difficulty":27.07,"equation":"10^3 - 10^2 * 19^0 = 900"},"901":{"difficulty":52.16,"equation":"10^3 - 10^2 + 19^0 = 901"},"919":{"difficulty":49.18,"equation":"10^3 - 10^2 + 19^1 = 919"},"971":{"difficulty":36.84,"equation":"10^3 - 10^1 - 19^1 = 971"},"980":{"difficulty":34.15,"equation":"10^3 - 10^0 - 19^1 = 980"},"981":{"difficulty":16.54,"equation":"10^0 * 10^3 - 19^1 = 981"},"982":{"difficulty":33.73,"equation":"10^0 + 10^3 - 19^1 = 982"},"989":{"difficulty":32.26,"equation":"10^3 - 10^1 - 19^0 = 989"},"990":{"difficulty":15.46,"equation":"10^3 - 10^1 * 19^0 = 990"},"991":{"difficulty":31.84,"equation":"10^3 - 10^1 + 19^0 = 991"},"998":{"difficulty":29.58,"equation":"10^3 - 10^0 - 19^0 = 998"},"999":{"difficulty":13.92,"equation":"10^0 * 10^3 - 19^0 = 999"}}}