{"dice":[3,18,20],"summary":{"solvableCount":370,"impossibleCount":629,"minDifficulty":-5.6,"maxDifficulty":100,"averageDifficulty":40.13},"solutions":{"1":{"difficulty":-5.6,"equation":"3^0 + 18^0 - 20^0 = 1"},"2":{"difficulty":-4.96,"equation":"3^0 + 18^0 * 20^0 = 2"},"3":{"difficulty":-4.59,"equation":"3^0 + 18^0 + 20^0 = 3"},"4":{"difficulty":-3.54,"equation":"3^1 + 18^0 * 20^0 = 4"},"5":{"difficulty":-3.08,"equation":"3^1 + 18^0 + 20^0 = 5"},"6":{"difficulty":-2.64,"equation":"18^0 + 20^0 * 3^1 = 6"},"7":{"difficulty":-1.16,"equation":"3^2 - 18^0 - 20^0 = 7"},"8":{"difficulty":-1.2,"equation":"3^2 - 18^0 * 20^0 = 8"},"9":{"difficulty":-1.26,"equation":"3^2 + 18^0 - 20^0 = 9"},"10":{"difficulty":-0.87,"equation":"3^2 + 18^0 * 20^0 = 10"},"11":{"difficulty":-0.49,"equation":"3^2 + 18^0 + 20^0 = 11"},"12":{"difficulty":1.49,"equation":"18^0 - 3^2 + 20^1 = 12"},"13":{"difficulty":47.27,"equation":"18^2 / 3^3 + 20^0 = 13"},"14":{"difficulty":-0.17,"equation":"18^1 - 3^1 - 20^0 = 14"},"15":{"difficulty":-0.26,"equation":"18^1 - 3^1 * 20^0 = 15"},"16":{"difficulty":-1.16,"equation":"18^1 - 3^0 - 20^0 = 16"},"17":{"difficulty":-1.26,"equation":"3^0 * 18^1 - 20^0 = 17"},"18":{"difficulty":-1.37,"equation":"3^0 + 18^1 - 20^0 = 18"},"19":{"difficulty":-1.02,"equation":"3^0 + 18^1 * 20^0 = 19"},"20":{"difficulty":-1.12,"equation":"3^0 - 18^0 + 20^1 = 20"},"21":{"difficulty":-0.78,"equation":"3^0 * 18^0 + 20^1 = 21"},"22":{"difficulty":-0.45,"equation":"3^0 + 18^0 + 20^1 = 22"},"23":{"difficulty":0.67,"equation":"3^1 * 18^0 + 20^1 = 23"},"24":{"difficulty":0.92,"equation":"3^1 + 18^0 + 20^1 = 24"},"25":{"difficulty":1.33,"equation":"3^3 - 18^0 - 20^0 = 25"},"26":{"difficulty":1.21,"equation":"3^3 - 18^0 * 20^0 = 26"},"27":{"difficulty":1.08,"equation":"3^3 + 18^0 - 20^0 = 27"},"28":{"difficulty":1.4,"equation":"3^3 + 18^0 * 20^0 = 28"},"29":{"difficulty":1.72,"equation":"3^3 + 18^0 + 20^0 = 29"},"30":{"difficulty":3.78,"equation":"3^2 + 18^0 + 20^1 = 30"},"32":{"difficulty":47.48,"equation":"18^2 / 3^3 + 20^1 = 32"},"34":{"difficulty":6.58,"equation":"3^1 * 18^1 - 20^1 = 34"},"35":{"difficulty":4.72,"equation":"18^1 - 3^1 + 20^1 = 35"},"36":{"difficulty":3.71,"equation":"3^0 + 20^0 * 18^1 = 36"},"37":{"difficulty":4.54,"equation":"18^1 - 3^0 + 20^1 = 37"},"38":{"difficulty":4.85,"equation":"3^0 * 18^1 + 20^1 = 38"},"39":{"difficulty":5.16,"equation":"3^0 + 18^1 + 20^1 = 39"},"40":{"difficulty":4.67,"equation":"3^0 + 18^0 * 20^1 = 40"},"41":{"difficulty":6.56,"equation":"3^1 + 18^1 + 20^1 = 41"},"42":{"difficulty":7.64,"equation":"3^1 * 20^1 - 18^1 = 42"},"43":{"difficulty":11.02,"equation":"3^4 - 18^1 - 20^1 = 43"},"44":{"difficulty":7.15,"equation":"3^3 + 18^1 - 20^0 = 44"},"45":{"difficulty":7.45,"equation":"3^3 + 18^1 * 20^0 = 45"},"46":{"difficulty":7.75,"equation":"3^3 - 18^0 + 20^1 = 46"},"47":{"difficulty":8.05,"equation":"3^3 * 18^0 + 20^1 = 47"},"48":{"difficulty":8.35,"equation":"3^3 + 18^0 + 20^1 = 48"},"49":{"difficulty":60.23,"equation":"20^2 - 3^3 - 18^2 = 49"},"50":{"difficulty":100,"equation":"3^6 / 18^3 * 20^2 = 50"},"51":{"difficulty":9.04,"equation":"18^1 - 20^0 * 3^1 = 51"},"52":{"difficulty":99.17,"equation":"18^3 / 3^4 - 20^1 = 52"},"53":{"difficulty":6.11,"equation":"3^1 * 18^1 - 20^0 = 53"},"54":{"difficulty":4.98,"equation":"3^1 * 18^1 * 20^0 = 54"},"55":{"difficulty":6.25,"equation":"3^1 * 18^1 + 20^0 = 55"},"56":{"difficulty":47.55,"equation":"18^2 / 3^2 + 20^1 = 56"},"57":{"difficulty":6.5,"equation":"20^0 + 18^1 * 3^1 = 57"},"59":{"difficulty":6.2,"equation":"3^1 * 20^1 - 18^0 = 59"},"60":{"difficulty":4.9,"equation":"3^1 * 20^1 * 18^0 = 60"},"61":{"difficulty":6.16,"equation":"3^1 * 20^1 + 18^0 = 61"},"62":{"difficulty":9.08,"equation":"3^4 + 18^0 - 20^1 = 62"},"63":{"difficulty":6.41,"equation":"18^0 + 20^1 * 3^1 = 63"},"64":{"difficulty":8.76,"equation":"3^4 - 18^1 + 20^0 = 64"},"65":{"difficulty":12.29,"equation":"3^3 + 18^1 + 20^1 = 65"},"67":{"difficulty":58.17,"equation":"20^2 - 3^2 - 18^2 = 67"},"68":{"difficulty":100,"equation":"18^4 / 3^7 + 20^1 = 68"},"71":{"difficulty":99.17,"equation":"18^3 / 3^4 - 20^0 = 71"},"72":{"difficulty":8.33,"equation":"20^0 + 3^1 * 18^1 = 72"},"73":{"difficulty":55.75,"equation":"20^2 - 3^1 - 18^2 = 73"},"74":{"difficulty":9.36,"equation":"3^1 * 18^1 + 20^1 = 74"},"75":{"difficulty":54.62,"equation":"20^2 - 3^0 - 18^2 = 75"},"76":{"difficulty":54.45,"equation":"3^0 * 20^2 - 18^2 = 76"},"77":{"difficulty":54.28,"equation":"3^0 - 18^2 + 20^2 = 77"},"78":{"difficulty":8.99,"equation":"3^1 * 20^1 + 18^1 = 78"},"79":{"difficulty":5.46,"equation":"3^4 - 18^0 - 20^0 = 79"},"80":{"difficulty":5.29,"equation":"3^4 - 18^0 * 20^0 = 80"},"81":{"difficulty":5.12,"equation":"3^4 + 18^0 - 20^0 = 81"},"82":{"difficulty":5.4,"equation":"3^4 + 18^0 * 20^0 = 82"},"83":{"difficulty":5.68,"equation":"3^4 + 18^0 + 20^0 = 83"},"85":{"difficulty":55.8,"equation":"3^2 - 18^2 + 20^2 = 85"},"86":{"difficulty":71.15,"equation":"3^3 * 18^1 - 20^2 = 86"},"88":{"difficulty":41.95,"equation":"18^2 / 3^1 - 20^1 = 88"},"90":{"difficulty":51.51,"equation":"3^4 / 18^1 * 20^1 = 90"},"92":{"difficulty":99.17,"equation":"18^3 / 3^4 + 20^1 = 92"},"95":{"difficulty":100,"equation":"18^5 / 3^9 - 20^0 = 95"},"96":{"difficulty":100,"equation":"18^5 / 3^9 * 20^0 = 96"},"97":{"difficulty":100,"equation":"18^5 / 3^9 + 20^0 = 97"},"98":{"difficulty":10.66,"equation":"3^4 + 18^1 - 20^0 = 98"},"99":{"difficulty":10.93,"equation":"3^4 + 18^1 * 20^0 = 99"},"100":{"difficulty":11.21,"equation":"3^4 - 18^0 + 20^1 = 100"},"101":{"difficulty":11.49,"equation":"3^4 * 18^0 + 20^1 = 101"},"102":{"difficulty":11.76,"equation":"3^4 + 18^0 + 20^1 = 102"},"103":{"difficulty":55.66,"equation":"3^3 - 18^2 + 20^2 = 103"},"107":{"difficulty":40.98,"equation":"18^2 / 3^1 - 20^0 = 107"},"108":{"difficulty":40.97,"equation":"18^2 / 3^1 * 20^0 = 108"},"109":{"difficulty":40.96,"equation":"18^2 / 3^1 + 20^0 = 109"},"114":{"difficulty":18.48,"equation":"18^1 + 20^1 * 3^1 = 114"},"116":{"difficulty":100,"equation":"18^5 / 3^9 + 20^1 = 116"},"117":{"difficulty":51.23,"equation":"18^1 * 20^1 - 3^5 = 117"},"119":{"difficulty":17.21,"equation":"3^4 + 18^1 + 20^1 = 119"},"120":{"difficulty":20.11,"equation":"18^1 / 3^1 * 20^1 = 120"},"124":{"difficulty":100,"equation":"18^4 / 3^6 - 20^1 = 124"},"126":{"difficulty":51.1,"equation":"3^3 - 20^1 * 18^1 = 126"},"128":{"difficulty":41.5,"equation":"18^2 / 3^1 + 20^1 = 128"},"133":{"difficulty":51.61,"equation":"20^2 - 18^0 / 3^1 = 133"},"135":{"difficulty":99.19,"equation":"3^7 / 18^2 * 20^1 = 135"},"139":{"difficulty":53.73,"equation":"20^2 - 3^5 - 18^1 = 139"},"142":{"difficulty":20.39,"equation":"3^2 * 18^1 - 20^1 = 142"},"143":{"difficulty":100,"equation":"18^4 / 3^6 - 20^0 = 143"},"144":{"difficulty":31.86,"equation":"3^2 - 20^0 * 18^1 = 144"},"145":{"difficulty":100,"equation":"18^4 / 3^6 + 20^0 = 145"},"150":{"difficulty":100,"equation":"3^7 / 18^3 * 20^2 = 150"},"153":{"difficulty":34.27,"equation":"18^1 - 20^0 * 3^2 = 153"},"156":{"difficulty":52.62,"equation":"20^2 - 3^5 - 18^0 = 156"},"157":{"difficulty":52.61,"equation":"18^0 * 20^2 - 3^5 = 157"},"158":{"difficulty":52.59,"equation":"18^0 - 3^5 + 20^2 = 158"},"160":{"difficulty":35.86,"equation":"3^2 - 18^0 * 20^1 = 160"},"161":{"difficulty":19.24,"equation":"3^2 * 18^1 - 20^0 = 161"},"162":{"difficulty":16.62,"equation":"3^2 * 18^1 * 20^0 = 162"},"163":{"difficulty":19.32,"equation":"3^2 * 18^1 + 20^0 = 163"},"164":{"difficulty":100,"equation":"18^4 / 3^6 + 20^1 = 164"},"167":{"difficulty":53.79,"equation":"3^5 + 18^2 - 20^2 = 167"},"171":{"difficulty":20.11,"equation":"20^0 + 18^1 * 3^2 = 171"},"175":{"difficulty":50.86,"equation":"18^1 - 3^5 + 20^2 = 175"},"179":{"difficulty":18.64,"equation":"3^2 * 20^1 - 18^0 = 179"},"180":{"difficulty":15.85,"equation":"3^2 * 20^1 * 18^0 = 180"},"181":{"difficulty":18.55,"equation":"3^2 * 20^1 + 18^0 = 181"},"182":{"difficulty":21.97,"equation":"3^2 * 18^1 + 20^1 = 182"},"189":{"difficulty":19.32,"equation":"18^0 + 20^1 * 3^2 = 189"},"196":{"difficulty":99.17,"equation":"18^3 / 3^3 - 20^1 = 196"},"198":{"difficulty":20.97,"equation":"3^2 * 20^1 + 18^1 = 198"},"200":{"difficulty":20.37,"equation":"18^0 + 3^2 * 20^1 = 200"},"205":{"difficulty":21.03,"equation":"3^5 - 18^1 - 20^1 = 205"},"215":{"difficulty":99.16,"equation":"18^3 / 3^3 - 20^0 = 215"},"216":{"difficulty":67.99,"equation":"3^3 * 20^1 - 18^2 = 216"},"217":{"difficulty":99.16,"equation":"18^3 / 3^3 + 20^0 = 217"},"222":{"difficulty":16.97,"equation":"3^5 - 18^0 - 20^1 = 222"},"223":{"difficulty":16.78,"equation":"3^5 * 18^0 - 20^1 = 223"},"224":{"difficulty":16.59,"equation":"3^5 + 18^0 - 20^1 = 224"},"225":{"difficulty":16.39,"equation":"3^5 - 18^1 * 20^0 = 225"},"226":{"difficulty":16.2,"equation":"3^5 - 18^1 + 20^0 = 226"},"228":{"difficulty":99.02,"equation":"20^2 - 18^2 * 3^1 = 228"},"236":{"difficulty":99.16,"equation":"18^3 / 3^3 + 20^1 = 236"},"240":{"difficulty":63.35,"equation":"18^2 / 3^3 * 20^1 = 240"},"241":{"difficulty":12.51,"equation":"3^5 - 18^0 - 20^0 = 241"},"242":{"difficulty":12.31,"equation":"3^5 - 18^0 * 20^0 = 242"},"243":{"difficulty":12.12,"equation":"3^5 + 18^0 - 20^0 = 243"},"244":{"difficulty":12.38,"equation":"3^5 + 18^0 * 20^0 = 244"},"245":{"difficulty":12.63,"equation":"3^5 + 18^0 + 20^0 = 245"},"248":{"difficulty":99.16,"equation":"18^3 / 3^2 - 20^2 = 248"},"260":{"difficulty":17.29,"equation":"3^5 + 18^1 - 20^0 = 260"},"261":{"difficulty":17.55,"equation":"3^5 + 18^1 * 20^0 = 261"},"262":{"difficulty":17.81,"equation":"3^5 - 18^0 + 20^1 = 262"},"263":{"difficulty":18.06,"equation":"3^5 * 18^0 + 20^1 = 263"},"264":{"difficulty":18.32,"equation":"3^5 + 18^0 + 20^1 = 264"},"268":{"difficulty":100,"equation":"18^5 / 3^8 - 20^1 = 268"},"270":{"difficulty":34.24,"equation":"3^5 / 18^1 * 20^1 = 270"},"277":{"difficulty":25.89,"equation":"18^2 - 3^3 - 20^1 = 277"},"279":{"difficulty":33.97,"equation":"18^1 * 20^1 - 3^4 = 279"},"281":{"difficulty":23.48,"equation":"3^5 + 18^1 + 20^1 = 281"},"287":{"difficulty":100,"equation":"18^5 / 3^8 - 20^0 = 287"},"288":{"difficulty":100,"equation":"18^5 / 3^8 * 20^0 = 288"},"289":{"difficulty":100,"equation":"18^5 / 3^8 + 20^0 = 289"},"295":{"difficulty":23.43,"equation":"18^2 - 3^2 - 20^1 = 295"},"296":{"difficulty":22.44,"equation":"18^2 - 3^3 - 20^0 = 296"},"297":{"difficulty":22.24,"equation":"18^2 - 3^3 * 20^0 = 297"},"298":{"difficulty":22.05,"equation":"18^2 - 3^3 + 20^0 = 298"},"300":{"difficulty":50.94,"equation":"18^1 - 3^1 * 20^1 = 300"},"301":{"difficulty":20.82,"equation":"18^2 - 3^1 - 20^1 = 301"},"303":{"difficulty":19.63,"equation":"18^2 - 3^0 - 20^1 = 303"},"304":{"difficulty":19.43,"equation":"3^0 * 18^2 - 20^1 = 304"},"305":{"difficulty":19.24,"equation":"3^0 + 18^2 - 20^1 = 305"},"306":{"difficulty":52.31,"equation":"20^1 - 3^1 * 18^1 = 306"},"307":{"difficulty":19.63,"equation":"3^1 + 18^2 - 20^1 = 307"},"308":{"difficulty":100,"equation":"18^5 / 3^8 + 20^1 = 308"},"311":{"difficulty":78.69,"equation":"3^6 - 18^1 - 20^2 = 311"},"313":{"difficulty":19.88,"equation":"3^2 + 18^2 - 20^1 = 313"},"314":{"difficulty":18.88,"equation":"18^2 - 3^2 - 20^0 = 314"},"315":{"difficulty":18.69,"equation":"18^2 - 3^2 * 20^0 = 315"},"316":{"difficulty":18.49,"equation":"18^2 - 3^2 + 20^0 = 316"},"317":{"difficulty":19.08,"equation":"18^2 - 3^3 + 20^1 = 317"},"318":{"difficulty":29.07,"equation":"20^2 - 3^4 - 18^0 = 318"},"319":{"difficulty":28.88,"equation":"18^0 * 20^2 - 3^4 = 319"},"320":{"difficulty":16.27,"equation":"18^2 - 3^1 - 20^0 = 320"},"321":{"difficulty":16.07,"equation":"18^2 - 3^1 * 20^0 = 321"},"322":{"difficulty":15.08,"equation":"18^2 - 3^0 - 20^0 = 322"},"323":{"difficulty":14.88,"equation":"3^0 * 18^2 - 20^0 = 323"},"324":{"difficulty":14.68,"equation":"3^0 + 18^2 - 20^0 = 324"},"325":{"difficulty":14.93,"equation":"3^0 + 18^2 * 20^0 = 325"},"326":{"difficulty":15.19,"equation":"3^0 + 18^2 + 20^0 = 326"},"327":{"difficulty":16.24,"equation":"3^1 + 18^2 * 20^0 = 327"},"328":{"difficulty":16.49,"equation":"3^1 + 18^2 + 20^0 = 328"},"329":{"difficulty":75.16,"equation":"3^6 * 18^0 - 20^2 = 329"},"330":{"difficulty":75.13,"equation":"3^6 + 18^0 - 20^2 = 330"},"331":{"difficulty":19.47,"equation":"3^3 + 18^2 - 20^1 = 331"},"332":{"difficulty":18.93,"equation":"3^2 + 18^2 - 20^0 = 332"},"333":{"difficulty":19.19,"equation":"3^2 + 18^2 * 20^0 = 333"},"334":{"difficulty":19.44,"equation":"3^2 + 18^2 + 20^0 = 334"},"335":{"difficulty":20.49,"equation":"18^2 - 3^2 + 20^1 = 335"},"337":{"difficulty":28.26,"equation":"18^1 - 3^4 + 20^2 = 337"},"340":{"difficulty":60.69,"equation":"18^1 - 3^0 * 20^1 = 340"},"341":{"difficulty":20.58,"equation":"18^2 - 3^1 + 20^1 = 341"},"342":{"difficulty":43.72,"equation":"18^1 + 20^1 * 3^2 = 342"},"343":{"difficulty":20.29,"equation":"18^2 - 3^0 + 20^1 = 343"},"344":{"difficulty":20.55,"equation":"3^0 * 18^2 + 20^1 = 344"},"345":{"difficulty":20.8,"equation":"3^0 + 18^2 + 20^1 = 345"},"347":{"difficulty":22.1,"equation":"3^1 + 18^2 + 20^1 = 347"},"350":{"difficulty":23.49,"equation":"3^3 + 18^2 - 20^0 = 350"},"351":{"difficulty":23.74,"equation":"3^3 + 18^2 * 20^0 = 351"},"352":{"difficulty":24,"equation":"3^3 + 18^2 + 20^0 = 352"},"353":{"difficulty":25.04,"equation":"3^2 + 18^2 + 20^1 = 353"},"355":{"difficulty":27.67,"equation":"20^2 - 3^3 - 18^1 = 355"},"357":{"difficulty":23.34,"equation":"18^1 * 20^1 - 3^1 = 357"},"359":{"difficulty":22.48,"equation":"18^1 * 20^1 - 3^0 = 359"},"360":{"difficulty":18.08,"equation":"18^1 * 20^1 * 3^0 = 360"},"361":{"difficulty":22.7,"equation":"18^1 * 20^1 + 3^0 = 361"},"363":{"difficulty":23.83,"equation":"18^1 * 20^1 + 3^1 = 363"},"369":{"difficulty":25.78,"equation":"18^1 * 20^1 + 3^2 = 369"},"371":{"difficulty":28.09,"equation":"3^3 + 18^2 + 20^1 = 371"},"372":{"difficulty":24.65,"equation":"20^2 - 3^3 - 18^0 = 372"},"373":{"difficulty":24.45,"equation":"18^0 * 20^2 - 3^3 = 373"},"374":{"difficulty":24.25,"equation":"18^0 - 3^3 + 20^2 = 374"},"378":{"difficulty":24.32,"equation":"3^0 + 20^1 * 18^1 = 378"},"379":{"difficulty":22.61,"equation":"20^2 - 3^1 - 18^1 = 379"},"380":{"difficulty":24.49,"equation":"3^0 + 18^1 * 20^1 = 380"},"381":{"difficulty":21.42,"equation":"20^2 - 3^0 - 18^1 = 381"},"382":{"difficulty":21.22,"equation":"3^0 * 20^2 - 18^1 = 382"},"383":{"difficulty":21.01,"equation":"3^0 - 18^1 + 20^2 = 383"},"384":{"difficulty":28.91,"equation":"3^1 * 20^1 + 18^2 = 384"},"385":{"difficulty":21.41,"equation":"3^1 - 18^1 + 20^2 = 385"},"387":{"difficulty":27.31,"equation":"18^1 * 20^1 + 3^3 = 387"},"390":{"difficulty":21.04,"equation":"20^2 - 3^2 - 18^0 = 390"},"391":{"difficulty":20.84,"equation":"18^0 * 20^2 - 3^2 = 391"},"392":{"difficulty":20.64,"equation":"18^0 - 3^2 + 20^2 = 392"},"396":{"difficulty":18.4,"equation":"20^2 - 3^1 - 18^0 = 396"},"397":{"difficulty":18.2,"equation":"18^0 * 20^2 - 3^1 = 397"},"398":{"difficulty":17.21,"equation":"20^2 - 3^0 - 18^0 = 398"},"399":{"difficulty":17.01,"equation":"3^0 * 20^2 - 18^0 = 399"},"400":{"difficulty":16.81,"equation":"3^0 - 18^0 + 20^2 = 400"},"401":{"difficulty":17.06,"equation":"3^0 * 18^0 + 20^2 = 401"},"402":{"difficulty":17.31,"equation":"3^0 + 18^0 + 20^2 = 402"},"403":{"difficulty":18.35,"equation":"3^1 * 18^0 + 20^2 = 403"},"404":{"difficulty":18.6,"equation":"3^1 + 18^0 + 20^2 = 404"},"405":{"difficulty":31.02,"equation":"3^4 + 18^2 * 20^0 = 405"},"406":{"difficulty":19.9,"equation":"18^1 / 3^1 + 20^2 = 406"},"408":{"difficulty":21.04,"equation":"3^2 - 18^0 + 20^2 = 408"},"409":{"difficulty":21.29,"equation":"3^2 * 18^0 + 20^2 = 409"},"410":{"difficulty":21.54,"equation":"3^2 + 18^0 + 20^2 = 410"},"412":{"difficulty":24.26,"equation":"18^2 / 3^3 + 20^2 = 412"},"414":{"difficulty":30.5,"equation":"3^1 + 20^1 * 18^1 = 414"},"415":{"difficulty":22.16,"equation":"18^1 - 3^1 + 20^2 = 415"},"416":{"difficulty":100,"equation":"18^4 / 3^8 + 20^2 = 416"},"417":{"difficulty":21.87,"equation":"18^1 - 3^0 + 20^2 = 417"},"418":{"difficulty":22.12,"equation":"3^0 * 18^1 + 20^2 = 418"},"419":{"difficulty":22.37,"equation":"3^0 + 18^1 + 20^2 = 419"},"420":{"difficulty":32,"equation":"3^1 + 18^1 * 20^1 = 420"},"421":{"difficulty":23.66,"equation":"3^1 + 18^1 + 20^2 = 421"},"424":{"difficulty":99.16,"equation":"18^3 / 3^5 + 20^2 = 424"},"425":{"difficulty":36.82,"equation":"3^4 + 18^2 + 20^1 = 425"},"426":{"difficulty":25.55,"equation":"3^3 - 18^0 + 20^2 = 426"},"427":{"difficulty":25.8,"equation":"3^3 * 18^0 + 20^2 = 427"},"428":{"difficulty":26.05,"equation":"3^3 + 18^0 + 20^2 = 428"},"431":{"difficulty":100,"equation":"18^4 / 3^5 - 20^0 = 431"},"432":{"difficulty":100,"equation":"18^4 / 3^5 * 20^0 = 432"},"433":{"difficulty":100,"equation":"18^4 / 3^5 + 20^0 = 433"},"436":{"difficulty":30.27,"equation":"18^2 / 3^2 + 20^2 = 436"},"441":{"difficulty":38.69,"equation":"18^1 * 20^1 + 3^4 = 441"},"445":{"difficulty":31.1,"equation":"3^3 + 18^1 + 20^2 = 445"},"448":{"difficulty":100,"equation":"18^4 / 3^7 + 20^2 = 448"},"450":{"difficulty":100,"equation":"3^8 / 18^3 * 20^2 = 450"},"452":{"difficulty":100,"equation":"18^4 / 3^5 + 20^1 = 452"},"454":{"difficulty":33.05,"equation":"3^1 * 18^1 + 20^2 = 454"},"459":{"difficulty":84.73,"equation":"18^1 - 20^0 * 3^3 = 459"},"463":{"difficulty":35.59,"equation":"3^4 - 18^1 + 20^2 = 463"},"464":{"difficulty":100,"equation":"18^5 / 3^7 - 20^2 = 464"},"466":{"difficulty":32.83,"equation":"3^3 * 18^1 - 20^1 = 466"},"468":{"difficulty":86.97,"equation":"3^3 - 20^0 * 18^1 = 468"},"472":{"difficulty":99.16,"equation":"18^3 / 3^4 + 20^2 = 472"},"480":{"difficulty":39.03,"equation":"3^4 - 18^0 + 20^2 = 480"},"481":{"difficulty":39.28,"equation":"3^4 * 18^0 + 20^2 = 481"},"482":{"difficulty":39.53,"equation":"3^4 + 18^0 + 20^2 = 482"},"485":{"difficulty":31.35,"equation":"3^3 * 18^1 - 20^0 = 485"},"486":{"difficulty":26.94,"equation":"3^3 * 18^1 * 20^0 = 486"},"487":{"difficulty":31.56,"equation":"3^3 * 18^1 + 20^0 = 487"},"496":{"difficulty":100,"equation":"18^5 / 3^9 + 20^2 = 496"},"499":{"difficulty":44.55,"equation":"3^4 + 18^1 + 20^2 = 499"},"504":{"difficulty":35.78,"equation":"20^0 + 3^3 * 18^1 = 504"},"506":{"difficulty":37.08,"equation":"3^3 * 18^1 + 20^1 = 506"},"508":{"difficulty":46.79,"equation":"18^2 / 3^1 + 20^2 = 508"},"513":{"difficulty":38.02,"equation":"20^0 + 18^1 * 3^3 = 513"},"520":{"difficulty":99.02,"equation":"3^3 - 18^0 * 20^1 = 520"},"522":{"difficulty":38.91,"equation":"3^3 * 20^1 - 18^1 = 522"},"539":{"difficulty":37.47,"equation":"3^3 * 20^1 - 18^0 = 539"},"540":{"difficulty":32.71,"equation":"3^3 * 20^1 * 18^0 = 540"},"541":{"difficulty":37.68,"equation":"3^3 * 20^1 + 18^0 = 541"},"544":{"difficulty":100,"equation":"18^4 / 3^6 + 20^2 = 544"},"547":{"difficulty":67.19,"equation":"3^5 + 18^2 - 20^1 = 547"},"558":{"difficulty":42.68,"equation":"3^3 * 20^1 + 18^1 = 558"},"560":{"difficulty":42.39,"equation":"18^0 + 3^3 * 20^1 = 560"},"562":{"difficulty":62.77,"equation":"3^2 * 18^1 + 20^2 = 562"},"566":{"difficulty":70.85,"equation":"3^5 + 18^2 - 20^0 = 566"},"567":{"difficulty":43.7,"equation":"18^0 + 20^1 * 3^3 = 567"},"568":{"difficulty":71.01,"equation":"3^5 + 18^2 + 20^0 = 568"},"572":{"difficulty":99.02,"equation":"3^1 * 18^2 - 20^2 = 572"},"587":{"difficulty":73.33,"equation":"3^5 + 18^2 + 20^1 = 587"},"600":{"difficulty":55.85,"equation":"20^2 / 18^1 * 3^3 = 600"},"603":{"difficulty":72.47,"equation":"18^1 * 20^1 + 3^5 = 603"},"616":{"difficulty":99.16,"equation":"18^3 / 3^3 + 20^2 = 616"},"625":{"difficulty":65.63,"equation":"3^5 - 18^1 + 20^2 = 625"},"628":{"difficulty":99.16,"equation":"18^3 / 3^2 - 20^1 = 628"},"639":{"difficulty":99.2,"equation":"18^1 * 20^2 - 3^8 = 639"},"642":{"difficulty":66.19,"equation":"3^5 - 18^0 + 20^2 = 642"},"643":{"difficulty":66.27,"equation":"3^5 * 18^0 + 20^2 = 643"},"644":{"difficulty":66.35,"equation":"3^5 + 18^0 + 20^2 = 644"},"647":{"difficulty":99.16,"equation":"18^3 / 3^2 - 20^0 = 647"},"648":{"difficulty":75.17,"equation":"3^0 + 20^0 * 18^2 = 648"},"649":{"difficulty":99.16,"equation":"18^3 / 3^2 + 20^0 = 649"},"653":{"difficulty":44.43,"equation":"3^6 + 18^2 - 20^2 = 653"},"661":{"difficulty":68.48,"equation":"3^5 + 18^1 + 20^2 = 661"},"668":{"difficulty":99.15,"equation":"18^3 / 3^2 + 20^1 = 668"},"684":{"difficulty":99.07,"equation":"20^2 - 18^2 * 3^2 = 684"},"688":{"difficulty":100,"equation":"18^5 / 3^8 + 20^2 = 688"},"691":{"difficulty":33.71,"equation":"3^6 - 18^1 - 20^1 = 691"},"697":{"difficulty":72.75,"equation":"18^2 - 3^3 + 20^2 = 697"},"708":{"difficulty":29.39,"equation":"3^6 - 18^0 - 20^1 = 708"},"709":{"difficulty":29.19,"equation":"3^6 * 18^0 - 20^1 = 709"},"710":{"difficulty":28.98,"equation":"3^6 + 18^0 - 20^1 = 710"},"711":{"difficulty":28.77,"equation":"3^6 - 18^1 * 20^0 = 711"},"712":{"difficulty":28.57,"equation":"3^6 - 18^1 + 20^0 = 712"},"715":{"difficulty":74.16,"equation":"18^2 - 3^2 + 20^2 = 715"},"720":{"difficulty":86.45,"equation":"18^2 / 3^2 * 20^1 = 720"},"721":{"difficulty":73.2,"equation":"18^2 - 3^1 + 20^2 = 721"},"723":{"difficulty":72.56,"equation":"18^2 - 3^0 + 20^2 = 723"},"724":{"difficulty":72.64,"equation":"3^0 * 18^2 + 20^2 = 724"},"725":{"difficulty":72.72,"equation":"3^0 + 18^2 + 20^2 = 725"},"727":{"difficulty":24.66,"equation":"3^6 - 18^0 - 20^0 = 727"},"728":{"difficulty":24.45,"equation":"3^6 - 18^0 * 20^0 = 728"},"729":{"difficulty":24.24,"equation":"3^6 + 18^0 - 20^0 = 729"},"730":{"difficulty":24.49,"equation":"3^6 + 18^0 * 20^0 = 730"},"731":{"difficulty":24.73,"equation":"3^6 + 18^0 + 20^0 = 731"},"733":{"difficulty":76.23,"equation":"3^2 + 18^2 + 20^2 = 733"},"746":{"difficulty":29.19,"equation":"3^6 + 18^1 - 20^0 = 746"},"747":{"difficulty":29.44,"equation":"3^6 + 18^1 * 20^0 = 747"},"748":{"difficulty":29.68,"equation":"3^6 - 18^0 + 20^1 = 748"},"749":{"difficulty":29.93,"equation":"3^6 * 18^0 + 20^1 = 749"},"750":{"difficulty":30.17,"equation":"3^6 + 18^0 + 20^1 = 750"},"751":{"difficulty":80.63,"equation":"3^3 + 18^2 + 20^2 = 751"},"767":{"difficulty":35.12,"equation":"3^6 + 18^1 + 20^1 = 767"},"800":{"difficulty":88.15,"equation":"3^0 + 18^0 * 20^2 = 800"},"805":{"difficulty":47.25,"equation":"3^6 - 18^2 + 20^2 = 805"},"810":{"difficulty":49.98,"equation":"3^6 / 18^1 * 20^1 = 810"},"832":{"difficulty":100,"equation":"18^4 / 3^5 + 20^2 = 832"},"844":{"difficulty":100,"equation":"18^5 / 3^7 - 20^1 = 844"},"846":{"difficulty":99.02,"equation":"3^3 + 20^1 * 18^1 = 846"},"863":{"difficulty":100,"equation":"18^5 / 3^7 - 20^0 = 863"},"864":{"difficulty":99.02,"equation":"3^3 * 20^1 + 18^2 = 864"},"865":{"difficulty":100,"equation":"18^5 / 3^7 + 20^0 = 865"},"876":{"difficulty":99.02,"equation":"3^1 * 20^2 - 18^2 = 876"},"884":{"difficulty":100,"equation":"18^5 / 3^7 + 20^1 = 884"},"886":{"difficulty":99.02,"equation":"3^3 * 18^1 + 20^2 = 886"},"896":{"difficulty":100,"equation":"18^4 / 3^4 - 20^2 = 896"},"900":{"difficulty":99.02,"equation":"3^3 + 18^1 * 20^1 = 900"},"912":{"difficulty":99.03,"equation":"18^2 - 20^1 * 3^1 = 912"},"952":{"difficulty":52.53,"equation":"3^1 * 18^2 - 20^1 = 952"},"960":{"difficulty":100,"equation":"18^4 / 3^7 * 20^1 = 960"},"967":{"difficulty":99.03,"equation":"3^5 + 18^2 + 20^2 = 967"},"969":{"difficulty":99.03,"equation":"18^2 - 20^0 * 3^1 = 969"},"971":{"difficulty":50.91,"equation":"3^1 * 18^2 - 20^0 = 971"},"972":{"difficulty":49.72,"equation":"3^1 * 18^2 * 20^0 = 972"},"973":{"difficulty":51.11,"equation":"3^1 * 18^2 + 20^0 = 973"},"975":{"difficulty":51.59,"equation":"20^0 + 18^2 * 3^1 = 975"},"992":{"difficulty":56.5,"equation":"3^1 * 18^2 + 20^1 = 992"}}}