{"dice":[3,3,3],"summary":{"solvableCount":188,"impossibleCount":811,"minDifficulty":-5.6,"maxDifficulty":99.02,"averageDifficulty":26.57},"solutions":{"1":{"difficulty":-5.6,"equation":"3^0 + 3^0 - 3^0 = 1"},"2":{"difficulty":-4.96,"equation":"3^0 + 3^0 * 3^0 = 2"},"3":{"difficulty":-4.59,"equation":"3^0 + 3^0 + 3^0 = 3"},"4":{"difficulty":-3.54,"equation":"3^0 * 3^0 + 3^1 = 4"},"5":{"difficulty":-3.08,"equation":"3^0 + 3^0 + 3^1 = 5"},"6":{"difficulty":-2.64,"equation":"3^0 + 3^0 * 3^1 = 6"},"7":{"difficulty":-1.59,"equation":"3^0 + 3^1 + 3^1 = 7"},"8":{"difficulty":-1.2,"equation":"3^0 * 3^2 - 3^0 = 8"},"9":{"difficulty":-1.89,"equation":"3^1 * 3^1 * 3^0 = 9"},"10":{"difficulty":-0.87,"equation":"3^0 * 3^0 + 3^2 = 10"},"11":{"difficulty":-0.49,"equation":"3^0 + 3^0 + 3^2 = 11"},"12":{"difficulty":0.03,"equation":"3^1 + 3^0 * 3^1 = 12"},"13":{"difficulty":1.05,"equation":"3^0 + 3^1 + 3^2 = 13"},"15":{"difficulty":2.56,"equation":"3^1 + 3^1 + 3^2 = 15"},"17":{"difficulty":3.9,"equation":"3^2 - 3^0 + 3^2 = 17"},"18":{"difficulty":2.02,"equation":"3^0 + 3^0 * 3^2 = 18"},"19":{"difficulty":4.27,"equation":"3^0 - 3^2 + 3^3 = 19"},"21":{"difficulty":3.41,"equation":"3^3 - 3^1 - 3^1 = 21"},"23":{"difficulty":2.37,"equation":"3^3 - 3^0 - 3^1 = 23"},"24":{"difficulty":2.25,"equation":"3^0 * 3^3 - 3^1 = 24"},"25":{"difficulty":1.33,"equation":"3^3 - 3^0 - 3^0 = 25"},"26":{"difficulty":1.21,"equation":"3^0 * 3^3 - 3^0 = 26"},"27":{"difficulty":1.08,"equation":"3^0 - 3^0 + 3^3 = 27"},"28":{"difficulty":1.4,"equation":"3^0 * 3^0 + 3^3 = 28"},"29":{"difficulty":1.72,"equation":"3^0 + 3^0 + 3^3 = 29"},"30":{"difficulty":2.83,"equation":"3^0 * 3^1 + 3^3 = 30"},"31":{"difficulty":3.15,"equation":"3^0 + 3^1 + 3^3 = 31"},"33":{"difficulty":4.57,"equation":"3^1 + 3^1 + 3^3 = 33"},"35":{"difficulty":5.83,"equation":"3^2 - 3^0 + 3^3 = 35"},"36":{"difficulty":5.85,"equation":"3^0 + 3^1 * 3^2 = 36"},"37":{"difficulty":6.45,"equation":"3^0 + 3^2 + 3^3 = 37"},"39":{"difficulty":7.86,"equation":"3^1 + 3^2 + 3^3 = 39"},"45":{"difficulty":11.1,"equation":"3^2 + 3^2 + 3^3 = 45"},"51":{"difficulty":11.47,"equation":"3^3 - 3^1 + 3^3 = 51"},"53":{"difficulty":11.26,"equation":"3^3 - 3^0 + 3^3 = 53"},"54":{"difficulty":9.34,"equation":"3^0 + 3^0 * 3^3 = 54"},"55":{"difficulty":11.64,"equation":"3^0 - 3^3 + 3^4 = 55"},"57":{"difficulty":12.11,"equation":"3^1 - 3^3 + 3^4 = 57"},"63":{"difficulty":12.57,"equation":"3^2 - 3^3 + 3^4 = 63"},"69":{"difficulty":10.15,"equation":"3^4 - 3^1 - 3^2 = 69"},"71":{"difficulty":9.03,"equation":"3^4 - 3^0 - 3^2 = 71"},"72":{"difficulty":8.86,"equation":"3^0 * 3^4 - 3^2 = 72"},"73":{"difficulty":8.69,"equation":"3^0 - 3^2 + 3^4 = 73"},"75":{"difficulty":7.72,"equation":"3^4 - 3^1 - 3^1 = 75"},"77":{"difficulty":6.59,"equation":"3^4 - 3^0 - 3^1 = 77"},"78":{"difficulty":6.42,"equation":"3^0 * 3^4 - 3^1 = 78"},"79":{"difficulty":5.46,"equation":"3^4 - 3^0 - 3^0 = 79"},"80":{"difficulty":5.29,"equation":"3^0 * 3^4 - 3^0 = 80"},"81":{"difficulty":5.12,"equation":"3^0 - 3^0 + 3^4 = 81"},"82":{"difficulty":5.4,"equation":"3^0 * 3^0 + 3^4 = 82"},"83":{"difficulty":5.68,"equation":"3^0 + 3^0 + 3^4 = 83"},"84":{"difficulty":6.76,"equation":"3^0 * 3^1 + 3^4 = 84"},"85":{"difficulty":7.04,"equation":"3^0 + 3^1 + 3^4 = 85"},"87":{"difficulty":8.39,"equation":"3^1 + 3^1 + 3^4 = 87"},"89":{"difficulty":9.58,"equation":"3^2 - 3^0 + 3^4 = 89"},"90":{"difficulty":9.86,"equation":"3^0 * 3^2 + 3^4 = 90"},"91":{"difficulty":10.14,"equation":"3^0 + 3^2 + 3^4 = 91"},"93":{"difficulty":11.49,"equation":"3^1 + 3^2 + 3^4 = 93"},"99":{"difficulty":14.58,"equation":"3^2 + 3^2 + 3^4 = 99"},"105":{"difficulty":14.81,"equation":"3^3 - 3^1 + 3^4 = 105"},"107":{"difficulty":14.57,"equation":"3^3 - 3^0 + 3^4 = 107"},"108":{"difficulty":14.55,"equation":"3^0 + 3^1 * 3^3 = 108"},"109":{"difficulty":15.11,"equation":"3^0 + 3^3 + 3^4 = 109"},"111":{"difficulty":16.46,"equation":"3^1 + 3^3 + 3^4 = 111"},"117":{"difficulty":19.52,"equation":"3^2 + 3^3 + 3^4 = 117"},"135":{"difficulty":24.4,"equation":"3^3 + 3^3 + 3^4 = 135"},"153":{"difficulty":29.22,"equation":"3^4 - 3^2 + 3^4 = 153"},"159":{"difficulty":29.39,"equation":"3^4 - 3^1 + 3^4 = 159"},"161":{"difficulty":29.12,"equation":"3^4 - 3^0 + 3^4 = 161"},"162":{"difficulty":27.17,"equation":"3^0 + 3^0 * 3^4 = 162"},"163":{"difficulty":29.49,"equation":"3^0 + 3^4 + 3^4 = 163"},"165":{"difficulty":30.03,"equation":"3^1 - 3^4 + 3^5 = 165"},"171":{"difficulty":30.34,"equation":"3^2 - 3^4 + 3^5 = 171"},"189":{"difficulty":26.94,"equation":"3^3 - 3^4 + 3^5 = 189"},"207":{"difficulty":23.5,"equation":"3^5 - 3^2 - 3^3 = 207"},"213":{"difficulty":20.93,"equation":"3^5 - 3^1 - 3^3 = 213"},"215":{"difficulty":19.75,"equation":"3^5 - 3^0 - 3^3 = 215"},"216":{"difficulty":19.56,"equation":"3^0 * 3^5 - 3^3 = 216"},"217":{"difficulty":19.36,"equation":"3^0 - 3^3 + 3^5 = 217"},"219":{"difficulty":19.77,"equation":"3^1 - 3^3 + 3^5 = 219"},"225":{"difficulty":20.05,"equation":"3^2 - 3^3 + 3^5 = 225"},"231":{"difficulty":17.46,"equation":"3^5 - 3^1 - 3^2 = 231"},"233":{"difficulty":16.28,"equation":"3^5 - 3^0 - 3^2 = 233"},"234":{"difficulty":16.08,"equation":"3^0 * 3^5 - 3^2 = 234"},"235":{"difficulty":15.89,"equation":"3^0 - 3^2 + 3^5 = 235"},"237":{"difficulty":14.87,"equation":"3^5 - 3^1 - 3^1 = 237"},"239":{"difficulty":13.69,"equation":"3^5 - 3^0 - 3^1 = 239"},"240":{"difficulty":13.49,"equation":"3^0 * 3^5 - 3^1 = 240"},"241":{"difficulty":12.51,"equation":"3^5 - 3^0 - 3^0 = 241"},"242":{"difficulty":12.31,"equation":"3^0 * 3^5 - 3^0 = 242"},"243":{"difficulty":12.12,"equation":"3^0 - 3^0 + 3^5 = 243"},"244":{"difficulty":12.38,"equation":"3^0 * 3^0 + 3^5 = 244"},"245":{"difficulty":12.63,"equation":"3^0 + 3^0 + 3^5 = 245"},"246":{"difficulty":13.69,"equation":"3^0 * 3^1 + 3^5 = 246"},"247":{"difficulty":13.94,"equation":"3^0 + 3^1 + 3^5 = 247"},"249":{"difficulty":15.25,"equation":"3^1 + 3^1 + 3^5 = 249"},"251":{"difficulty":16.4,"equation":"3^2 - 3^0 + 3^5 = 251"},"252":{"difficulty":16.66,"equation":"3^0 * 3^2 + 3^5 = 252"},"253":{"difficulty":16.92,"equation":"3^0 + 3^2 + 3^5 = 253"},"255":{"difficulty":18.23,"equation":"3^1 + 3^2 + 3^5 = 255"},"261":{"difficulty":21.2,"equation":"3^2 + 3^2 + 3^5 = 261"},"267":{"difficulty":21.31,"equation":"3^3 - 3^1 + 3^5 = 267"},"269":{"difficulty":21.03,"equation":"3^3 - 3^0 + 3^5 = 269"},"270":{"difficulty":21.29,"equation":"3^0 * 3^3 + 3^5 = 270"},"271":{"difficulty":21.55,"equation":"3^0 + 3^3 + 3^5 = 271"},"273":{"difficulty":22.85,"equation":"3^1 + 3^3 + 3^5 = 273"},"279":{"difficulty":25.82,"equation":"3^2 + 3^3 + 3^5 = 279"},"297":{"difficulty":30.42,"equation":"3^3 + 3^3 + 3^5 = 297"},"315":{"difficulty":35.01,"equation":"3^4 - 3^2 + 3^5 = 315"},"321":{"difficulty":35.11,"equation":"3^4 - 3^1 + 3^5 = 321"},"323":{"difficulty":34.82,"equation":"3^4 - 3^0 + 3^5 = 323"},"324":{"difficulty":34.78,"equation":"3^0 + 3^1 * 3^4 = 324"},"325":{"difficulty":35.33,"equation":"3^0 + 3^4 + 3^5 = 325"},"327":{"difficulty":36.63,"equation":"3^1 + 3^4 + 3^5 = 327"},"333":{"difficulty":39.58,"equation":"3^2 + 3^4 + 3^5 = 333"},"351":{"difficulty":44.14,"equation":"3^3 + 3^4 + 3^5 = 351"},"405":{"difficulty":57.74,"equation":"3^4 + 3^4 + 3^5 = 405"},"459":{"difficulty":71.26,"equation":"3^5 - 3^3 + 3^5 = 459"},"477":{"difficulty":75.74,"equation":"3^5 - 3^2 + 3^5 = 477"},"483":{"difficulty":75.81,"equation":"3^5 - 3^1 + 3^5 = 483"},"485":{"difficulty":75.51,"equation":"3^5 - 3^0 + 3^5 = 485"},"486":{"difficulty":73.54,"equation":"3^0 + 3^0 * 3^5 = 486"},"487":{"difficulty":75.84,"equation":"3^0 + 3^5 + 3^5 = 487"},"489":{"difficulty":76.66,"equation":"3^1 - 3^5 + 3^6 = 489"},"495":{"difficulty":76.86,"equation":"3^2 - 3^5 + 3^6 = 495"},"513":{"difficulty":73.19,"equation":"3^3 - 3^5 + 3^6 = 513"},"567":{"difficulty":62.14,"equation":"3^4 - 3^5 + 3^6 = 567"},"621":{"difficulty":51.04,"equation":"3^6 - 3^3 - 3^4 = 621"},"639":{"difficulty":47.32,"equation":"3^6 - 3^2 - 3^4 = 639"},"645":{"difficulty":44.66,"equation":"3^6 - 3^1 - 3^4 = 645"},"647":{"difficulty":43.45,"equation":"3^6 - 3^0 - 3^4 = 647"},"648":{"difficulty":43.24,"equation":"3^0 * 3^6 - 3^4 = 648"},"649":{"difficulty":43.04,"equation":"3^0 - 3^4 + 3^6 = 649"},"651":{"difficulty":43.42,"equation":"3^1 - 3^4 + 3^6 = 651"},"657":{"difficulty":43.61,"equation":"3^2 - 3^4 + 3^6 = 657"},"675":{"difficulty":39.88,"equation":"3^3 - 3^4 + 3^6 = 675"},"693":{"difficulty":36.16,"equation":"3^6 - 3^2 - 3^3 = 693"},"699":{"difficulty":33.48,"equation":"3^6 - 3^1 - 3^3 = 699"},"701":{"difficulty":32.28,"equation":"3^6 - 3^0 - 3^3 = 701"},"702":{"difficulty":32.07,"equation":"3^0 * 3^6 - 3^3 = 702"},"703":{"difficulty":31.86,"equation":"3^0 - 3^3 + 3^6 = 703"},"705":{"difficulty":32.24,"equation":"3^1 - 3^3 + 3^6 = 705"},"711":{"difficulty":32.42,"equation":"3^2 - 3^3 + 3^6 = 711"},"717":{"difficulty":29.75,"equation":"3^6 - 3^1 - 3^2 = 717"},"719":{"difficulty":28.54,"equation":"3^6 - 3^0 - 3^2 = 719"},"720":{"difficulty":28.33,"equation":"3^0 * 3^6 - 3^2 = 720"},"721":{"difficulty":28.13,"equation":"3^0 - 3^2 + 3^6 = 721"},"723":{"difficulty":27.08,"equation":"3^6 - 3^1 - 3^1 = 723"},"725":{"difficulty":25.87,"equation":"3^6 - 3^0 - 3^1 = 725"},"726":{"difficulty":25.66,"equation":"3^0 * 3^6 - 3^1 = 726"},"727":{"difficulty":24.66,"equation":"3^6 - 3^0 - 3^0 = 727"},"728":{"difficulty":24.45,"equation":"3^0 * 3^6 - 3^0 = 728"},"729":{"difficulty":24.24,"equation":"3^0 - 3^0 + 3^6 = 729"},"730":{"difficulty":24.49,"equation":"3^0 * 3^0 + 3^6 = 730"},"731":{"difficulty":24.73,"equation":"3^0 + 3^0 + 3^6 = 731"},"732":{"difficulty":25.77,"equation":"3^0 * 3^1 + 3^6 = 732"},"733":{"difficulty":26.02,"equation":"3^0 + 3^1 + 3^6 = 733"},"735":{"difficulty":27.3,"equation":"3^1 + 3^1 + 3^6 = 735"},"737":{"difficulty":28.42,"equation":"3^2 - 3^0 + 3^6 = 737"},"738":{"difficulty":28.67,"equation":"3^0 * 3^2 + 3^6 = 738"},"739":{"difficulty":28.91,"equation":"3^0 + 3^2 + 3^6 = 739"},"741":{"difficulty":30.19,"equation":"3^1 + 3^2 + 3^6 = 741"},"747":{"difficulty":33.09,"equation":"3^2 + 3^2 + 3^6 = 747"},"753":{"difficulty":33.13,"equation":"3^3 - 3^1 + 3^6 = 753"},"755":{"difficulty":32.82,"equation":"3^3 - 3^0 + 3^6 = 755"},"756":{"difficulty":33.07,"equation":"3^0 * 3^3 + 3^6 = 756"},"757":{"difficulty":33.31,"equation":"3^0 + 3^3 + 3^6 = 757"},"759":{"difficulty":34.59,"equation":"3^1 + 3^3 + 3^6 = 759"},"765":{"difficulty":37.49,"equation":"3^2 + 3^3 + 3^6 = 765"},"783":{"difficulty":41.88,"equation":"3^3 + 3^3 + 3^6 = 783"},"801":{"difficulty":46.28,"equation":"3^4 - 3^2 + 3^6 = 801"},"807":{"difficulty":46.31,"equation":"3^4 - 3^1 + 3^6 = 807"},"809":{"difficulty":46,"equation":"3^4 - 3^0 + 3^6 = 809"},"810":{"difficulty":46.25,"equation":"3^0 * 3^4 + 3^6 = 810"},"811":{"difficulty":46.49,"equation":"3^0 + 3^4 + 3^6 = 811"},"813":{"difficulty":47.77,"equation":"3^1 + 3^4 + 3^6 = 813"},"819":{"difficulty":50.66,"equation":"3^2 + 3^4 + 3^6 = 819"},"837":{"difficulty":55.05,"equation":"3^3 + 3^4 + 3^6 = 837"},"891":{"difficulty":68.18,"equation":"3^4 + 3^4 + 3^6 = 891"},"945":{"difficulty":81.29,"equation":"3^5 - 3^3 + 3^6 = 945"},"963":{"difficulty":85.65,"equation":"3^5 - 3^2 + 3^6 = 963"},"969":{"difficulty":85.67,"equation":"3^5 - 3^1 + 3^6 = 969"},"971":{"difficulty":85.36,"equation":"3^5 - 3^0 + 3^6 = 971"},"972":{"difficulty":85.32,"equation":"3^0 + 3^1 * 3^5 = 972"},"973":{"difficulty":85.85,"equation":"3^0 + 3^5 + 3^6 = 973"},"975":{"difficulty":87.13,"equation":"3^1 + 3^5 + 3^6 = 975"},"981":{"difficulty":99.02,"equation":"3^2 + 3^5 + 3^6 = 981"},"999":{"difficulty":99.02,"equation":"3^3 + 3^5 + 3^6 = 999"}}}