{"dice":[4,5,6],"summary":{"solvableCount":534,"impossibleCount":465,"minDifficulty":-5.6,"maxDifficulty":100,"averageDifficulty":37.67},"solutions":{"1":{"difficulty":-5.6,"equation":"4^0 + 5^0 - 6^0 = 1"},"2":{"difficulty":-4.96,"equation":"4^0 + 5^0 * 6^0 = 2"},"3":{"difficulty":-4.5,"equation":"4^0 + 5^0 + 6^0 = 3"},"4":{"difficulty":-3.75,"equation":"4^1 + 5^0 - 6^0 = 4"},"5":{"difficulty":-3.5,"equation":"4^0 + 5^1 - 6^0 = 5"},"6":{"difficulty":-3.27,"equation":"4^0 - 5^0 + 6^1 = 6"},"7":{"difficulty":-2.85,"equation":"4^0 * 5^0 + 6^1 = 7"},"8":{"difficulty":-2.44,"equation":"4^0 + 5^0 + 6^1 = 8"},"9":{"difficulty":-1.25,"equation":"4^1 - 5^0 + 6^1 = 9"},"10":{"difficulty":-1.52,"equation":"4^0 + 6^0 * 5^1 = 10"},"11":{"difficulty":-0.48,"equation":"4^0 * 5^1 + 6^1 = 11"},"12":{"difficulty":-1.07,"equation":"4^0 + 5^0 * 6^1 = 12"},"13":{"difficulty":7.99,"equation":"4^3 + 6^0 / 5^1 = 13"},"14":{"difficulty":0,"equation":"4^2 - 5^0 - 6^0 = 14"},"15":{"difficulty":-0.1,"equation":"4^2 - 5^0 * 6^0 = 15"},"16":{"difficulty":-0.19,"equation":"4^2 + 5^0 - 6^0 = 16"},"17":{"difficulty":0.15,"equation":"4^2 + 5^0 * 6^0 = 17"},"18":{"difficulty":0.5,"equation":"4^2 + 5^0 + 6^0 = 18"},"19":{"difficulty":1.37,"equation":"4^1 * 5^1 - 6^0 = 19"},"20":{"difficulty":0.01,"equation":"4^1 * 5^1 * 6^0 = 20"},"21":{"difficulty":1.67,"equation":"4^1 * 5^1 + 6^0 = 21"},"22":{"difficulty":2.03,"equation":"5^2 - 4^1 + 6^0 = 22"},"23":{"difficulty":1.12,"equation":"5^2 - 4^0 - 6^0 = 23"},"24":{"difficulty":0.21,"equation":"4^1 * 6^1 * 5^0 = 24"},"25":{"difficulty":0.87,"equation":"4^0 + 5^2 - 6^0 = 25"},"26":{"difficulty":1.19,"equation":"4^0 + 5^2 * 6^0 = 26"},"27":{"difficulty":1.52,"equation":"4^0 + 5^2 + 6^0 = 27"},"28":{"difficulty":2.63,"equation":"4^1 + 5^2 - 6^0 = 28"},"29":{"difficulty":2.8,"equation":"5^1 * 6^1 - 4^0 = 29"},"30":{"difficulty":1.16,"equation":"5^1 * 6^1 * 4^0 = 30"},"31":{"difficulty":3.06,"equation":"5^1 * 6^1 + 4^0 = 31"},"32":{"difficulty":3.29,"equation":"4^0 - 5^1 + 6^2 = 32"},"33":{"difficulty":3.15,"equation":"5^0 - 4^1 + 6^2 = 33"},"34":{"difficulty":2.21,"equation":"6^2 - 4^0 - 5^0 = 34"},"35":{"difficulty":2.07,"equation":"4^0 * 6^2 - 5^0 = 35"},"36":{"difficulty":1.93,"equation":"4^0 - 5^0 + 6^2 = 36"},"37":{"difficulty":2.24,"equation":"4^0 * 5^0 + 6^2 = 37"},"38":{"difficulty":2.55,"equation":"4^0 + 5^0 + 6^2 = 38"},"39":{"difficulty":3.65,"equation":"4^1 - 5^0 + 6^2 = 39"},"40":{"difficulty":3.95,"equation":"4^1 * 5^0 + 6^2 = 40"},"41":{"difficulty":4.26,"equation":"4^0 * 5^1 + 6^2 = 41"},"42":{"difficulty":4.56,"equation":"4^0 + 5^1 + 6^2 = 42"},"43":{"difficulty":29.12,"equation":"6^3 - 4^0 / 5^1 = 43"},"44":{"difficulty":7.59,"equation":"5^1 + 6^1 * 4^1 = 44"},"45":{"difficulty":6.26,"equation":"4^1 + 5^1 + 6^2 = 45"},"46":{"difficulty":9.06,"equation":"5^1 * 6^1 + 4^2 = 46"},"47":{"difficulty":8.29,"equation":"4^2 - 5^1 + 6^2 = 47"},"49":{"difficulty":10.38,"equation":"4^1 * 6^1 + 5^2 = 49"},"50":{"difficulty":7.68,"equation":"4^0 + 6^0 * 5^2 = 50"},"51":{"difficulty":8.52,"equation":"4^2 - 5^0 + 6^2 = 51"},"52":{"difficulty":8.65,"equation":"4^2 * 5^0 + 6^2 = 52"},"53":{"difficulty":7.41,"equation":"4^3 - 5^1 - 6^1 = 53"},"54":{"difficulty":9.34,"equation":"4^1 + 5^1 * 6^1 = 54"},"55":{"difficulty":17.44,"equation":"5^3 - 4^3 - 6^1 = 55"},"56":{"difficulty":9.94,"equation":"4^1 * 5^1 + 6^2 = 56"},"57":{"difficulty":5.98,"equation":"4^3 - 5^0 - 6^1 = 57"},"58":{"difficulty":5.82,"equation":"4^3 * 5^0 - 6^1 = 58"},"59":{"difficulty":5.66,"equation":"4^3 + 5^0 - 6^1 = 59"},"60":{"difficulty":5.5,"equation":"4^3 - 5^1 + 6^0 = 60"},"61":{"difficulty":9.78,"equation":"4^0 * 5^2 + 6^2 = 61"},"62":{"difficulty":4.38,"equation":"4^3 - 5^0 - 6^0 = 62"},"63":{"difficulty":4.22,"equation":"4^3 - 5^0 * 6^0 = 63"},"64":{"difficulty":4.06,"equation":"4^3 + 5^0 - 6^0 = 64"},"65":{"difficulty":4.34,"equation":"4^3 + 5^0 * 6^0 = 65"},"66":{"difficulty":4.63,"equation":"4^3 + 5^0 + 6^0 = 66"},"67":{"difficulty":15.99,"equation":"5^3 - 4^3 + 6^1 = 67"},"68":{"difficulty":6,"equation":"4^3 + 5^1 - 6^0 = 68"},"69":{"difficulty":6.29,"equation":"4^3 - 5^0 + 6^1 = 69"},"70":{"difficulty":6.57,"equation":"4^3 * 5^0 + 6^1 = 70"},"71":{"difficulty":6.86,"equation":"4^3 + 5^0 + 6^1 = 71"},"72":{"difficulty":10.23,"equation":"4^0 + 5^0 * 6^2 = 72"},"73":{"difficulty":17.42,"equation":"5^3 - 4^2 - 6^2 = 73"},"74":{"difficulty":9.67,"equation":"4^2 * 5^1 - 6^1 = 74"},"75":{"difficulty":8.79,"equation":"4^3 + 5^1 + 6^1 = 75"},"76":{"difficulty":15.87,"equation":"5^2 - 6^1 * 4^1 = 76"},"77":{"difficulty":16.09,"equation":"4^2 + 5^2 + 6^2 = 77"},"79":{"difficulty":8.86,"equation":"4^2 * 5^1 - 6^0 = 79"},"80":{"difficulty":7.19,"equation":"4^2 * 5^1 * 6^0 = 80"},"81":{"difficulty":9.14,"equation":"4^2 * 5^1 + 6^0 = 81"},"82":{"difficulty":99.04,"equation":"6^4 / 4^2 + 5^0 = 82"},"83":{"difficulty":12.48,"equation":"4^3 + 5^2 - 6^1 = 83"},"85":{"difficulty":10.26,"equation":"6^0 + 4^2 * 5^1 = 85"},"86":{"difficulty":11.34,"equation":"4^2 * 5^1 + 6^1 = 86"},"87":{"difficulty":29.16,"equation":"6^3 - 4^1 - 5^3 = 87"},"88":{"difficulty":13.09,"equation":"4^3 + 5^2 - 6^0 = 88"},"89":{"difficulty":13.37,"equation":"4^3 + 5^2 * 6^0 = 89"},"90":{"difficulty":13.65,"equation":"4^3 + 5^2 + 6^0 = 90"},"91":{"difficulty":12.18,"equation":"4^2 * 6^1 - 5^1 = 91"},"92":{"difficulty":28.34,"equation":"4^0 - 5^3 + 6^3 = 92"},"93":{"difficulty":15.9,"equation":"4^1 + 5^3 - 6^2 = 93"},"94":{"difficulty":12.23,"equation":"4^1 * 5^2 - 6^1 = 94"},"95":{"difficulty":11.27,"equation":"4^2 * 6^1 - 5^0 = 95"},"96":{"difficulty":9.18,"equation":"4^2 * 6^1 * 5^0 = 96"},"97":{"difficulty":11.2,"equation":"4^2 * 6^1 + 5^0 = 97"},"99":{"difficulty":10.65,"equation":"4^1 * 5^2 - 6^0 = 99"},"100":{"difficulty":9.06,"equation":"4^1 * 5^2 * 6^0 = 100"},"101":{"difficulty":10.58,"equation":"4^1 * 5^2 + 6^0 = 101"},"102":{"difficulty":11.75,"equation":"5^0 + 4^2 * 6^1 = 102"},"103":{"difficulty":14.4,"equation":"5^3 - 4^2 - 6^1 = 103"},"104":{"difficulty":10.91,"equation":"6^0 + 5^2 * 4^1 = 104"},"105":{"difficulty":15.47,"equation":"4^2 + 5^3 - 6^2 = 105"},"106":{"difficulty":11.92,"equation":"4^1 * 5^2 + 6^1 = 106"},"107":{"difficulty":28.33,"equation":"4^2 - 5^3 + 6^3 = 107"},"108":{"difficulty":12.71,"equation":"5^3 - 4^2 - 6^0 = 108"},"109":{"difficulty":12.54,"equation":"5^3 - 4^2 * 6^0 = 109"},"110":{"difficulty":12.36,"equation":"5^3 - 4^2 + 6^0 = 110"},"112":{"difficulty":12.83,"equation":"5^0 + 6^1 * 4^2 = 112"},"115":{"difficulty":10.83,"equation":"5^3 - 4^1 - 6^1 = 115"},"116":{"difficulty":17.47,"equation":"4^2 * 5^1 + 6^2 = 116"},"118":{"difficulty":9.49,"equation":"5^3 - 4^0 - 6^1 = 118"},"119":{"difficulty":9.31,"equation":"4^0 * 5^3 - 6^1 = 119"},"120":{"difficulty":9.13,"equation":"4^0 + 5^3 - 6^1 = 120"},"121":{"difficulty":8.95,"equation":"5^3 - 4^1 * 6^0 = 121"},"122":{"difficulty":8.77,"equation":"5^3 - 4^1 + 6^0 = 122"},"123":{"difficulty":7.8,"equation":"5^3 - 4^0 - 6^0 = 123"},"124":{"difficulty":7.62,"equation":"4^0 * 5^3 - 6^0 = 124"},"125":{"difficulty":7.43,"equation":"4^0 + 5^3 - 6^0 = 125"},"126":{"difficulty":7.71,"equation":"4^0 + 5^3 * 6^0 = 126"},"127":{"difficulty":7.98,"equation":"4^0 + 5^3 + 6^0 = 127"},"128":{"difficulty":9.04,"equation":"4^1 + 5^3 - 6^0 = 128"},"129":{"difficulty":9.31,"equation":"4^1 + 5^3 * 6^0 = 129"},"130":{"difficulty":9.58,"equation":"4^1 + 5^3 + 6^0 = 130"},"131":{"difficulty":9.85,"equation":"4^0 * 5^3 + 6^1 = 131"},"132":{"difficulty":10.12,"equation":"4^0 + 5^3 + 6^1 = 132"},"134":{"difficulty":12.88,"equation":"6^2 / 4^1 + 5^3 = 134"},"135":{"difficulty":11.72,"equation":"4^1 + 5^3 + 6^1 = 135"},"136":{"difficulty":18.33,"equation":"4^1 * 5^2 + 6^2 = 136"},"137":{"difficulty":29.28,"equation":"4^4 - 5^3 + 6^1 = 137"},"139":{"difficulty":12.98,"equation":"4^1 * 6^2 - 5^1 = 139"},"140":{"difficulty":13.7,"equation":"4^2 + 5^3 - 6^0 = 140"},"141":{"difficulty":13.97,"equation":"4^2 + 5^3 * 6^0 = 141"},"142":{"difficulty":14.24,"equation":"4^2 + 5^3 + 6^0 = 142"},"143":{"difficulty":12.11,"equation":"4^1 * 6^2 - 5^0 = 143"},"144":{"difficulty":10.68,"equation":"4^1 * 6^2 * 5^0 = 144"},"145":{"difficulty":12.36,"equation":"4^1 * 6^2 + 5^0 = 145"},"146":{"difficulty":14.23,"equation":"5^2 * 6^1 - 4^1 = 146"},"147":{"difficulty":16.37,"equation":"4^2 + 5^3 + 6^1 = 147"},"148":{"difficulty":13.17,"equation":"5^0 + 6^2 * 4^1 = 148"},"149":{"difficulty":13.38,"equation":"5^2 * 6^1 - 4^0 = 149"},"150":{"difficulty":11.45,"equation":"5^2 * 6^1 * 4^0 = 150"},"151":{"difficulty":13.63,"equation":"5^2 * 6^1 + 4^0 = 151"},"152":{"difficulty":22.42,"equation":"5^0 * 6^3 - 4^3 = 152"},"153":{"difficulty":19.4,"equation":"4^3 + 5^3 - 6^2 = 153"},"154":{"difficulty":15.22,"equation":"5^2 * 6^1 + 4^1 = 154"},"155":{"difficulty":24.58,"equation":"4^3 - 5^3 + 6^3 = 155"},"156":{"difficulty":14.96,"equation":"4^0 + 5^2 * 6^1 = 156"},"157":{"difficulty":19.04,"equation":"5^3 - 4^1 + 6^2 = 157"},"160":{"difficulty":19.04,"equation":"5^3 - 4^0 + 6^2 = 160"},"161":{"difficulty":19.31,"equation":"4^0 * 5^3 + 6^2 = 161"},"162":{"difficulty":19.57,"equation":"4^0 + 5^3 + 6^2 = 162"},"164":{"difficulty":18.22,"equation":"5^1 + 6^2 * 4^1 = 164"},"165":{"difficulty":21.16,"equation":"4^1 + 5^3 + 6^2 = 165"},"166":{"difficulty":19.84,"equation":"5^2 * 6^1 + 4^2 = 166"},"167":{"difficulty":30.14,"equation":"4^4 - 5^3 + 6^2 = 167"},"169":{"difficulty":20.97,"equation":"4^1 * 6^2 + 5^2 = 169"},"174":{"difficulty":19.94,"equation":"4^1 + 5^2 * 6^1 = 174"},"175":{"difficulty":19.25,"equation":"4^0 + 6^1 * 5^2 = 175"},"176":{"difficulty":16.82,"equation":"5^1 * 6^2 - 4^1 = 176"},"177":{"difficulty":23.04,"equation":"5^2 - 4^3 + 6^3 = 177"},"179":{"difficulty":15.46,"equation":"5^1 * 6^2 - 4^0 = 179"},"180":{"difficulty":13.6,"equation":"5^1 * 6^2 * 4^0 = 180"},"181":{"difficulty":15.37,"equation":"5^1 * 6^2 + 4^0 = 181"},"183":{"difficulty":23.83,"equation":"4^3 + 5^3 - 6^1 = 183"},"184":{"difficulty":16.46,"equation":"5^1 * 6^2 + 4^1 = 184"},"185":{"difficulty":15.76,"equation":"4^0 + 6^2 * 5^1 = 185"},"187":{"difficulty":19.72,"equation":"6^3 - 4^1 - 5^2 = 187"},"188":{"difficulty":23.52,"equation":"4^3 + 5^3 - 6^0 = 188"},"189":{"difficulty":23.62,"equation":"4^3 + 5^3 * 6^0 = 189"},"190":{"difficulty":18.36,"equation":"6^3 - 4^0 - 5^2 = 190"},"191":{"difficulty":18.17,"equation":"4^0 * 6^3 - 5^2 = 191"},"192":{"difficulty":17.98,"equation":"4^0 - 5^2 + 6^3 = 192"},"195":{"difficulty":18.2,"equation":"4^1 - 5^2 + 6^3 = 195"},"196":{"difficulty":19.03,"equation":"5^1 * 6^2 + 4^2 = 196"},"199":{"difficulty":16.65,"equation":"6^3 - 4^2 - 5^0 = 199"},"200":{"difficulty":16.46,"equation":"5^0 * 6^3 - 4^2 = 200"},"201":{"difficulty":16.27,"equation":"5^0 - 4^2 + 6^3 = 201"},"205":{"difficulty":16.3,"equation":"5^1 - 4^2 + 6^3 = 205"},"206":{"difficulty":99.03,"equation":"4^5 + 6^1 / 5^1 = 206"},"207":{"difficulty":14.48,"equation":"6^3 - 4^1 - 5^1 = 207"},"208":{"difficulty":99.03,"equation":"6^4 - 4^4 / 5^1 = 208"},"210":{"difficulty":13.12,"equation":"6^3 - 4^0 - 5^1 = 210"},"211":{"difficulty":12.92,"equation":"4^0 * 6^3 - 5^1 = 211"},"212":{"difficulty":12.73,"equation":"4^0 - 5^1 + 6^3 = 212"},"213":{"difficulty":12.54,"equation":"5^0 - 4^1 + 6^3 = 213"},"214":{"difficulty":11.56,"equation":"6^3 - 4^0 - 5^0 = 214"},"215":{"difficulty":11.36,"equation":"4^0 * 6^3 - 5^0 = 215"},"216":{"difficulty":11.17,"equation":"4^0 - 5^0 + 6^3 = 216"},"217":{"difficulty":11.43,"equation":"4^0 * 5^0 + 6^3 = 217"},"218":{"difficulty":11.69,"equation":"4^0 + 5^0 + 6^3 = 218"},"219":{"difficulty":12.74,"equation":"4^1 - 5^0 + 6^3 = 219"},"220":{"difficulty":13,"equation":"4^1 * 5^0 + 6^3 = 220"},"221":{"difficulty":13.26,"equation":"4^0 * 5^1 + 6^3 = 221"},"222":{"difficulty":13.52,"equation":"4^0 + 5^1 + 6^3 = 222"},"224":{"difficulty":99.23,"equation":"4^3 * 5^3 - 6^5 = 224"},"225":{"difficulty":15.1,"equation":"4^1 + 5^1 + 6^3 = 225"},"227":{"difficulty":17.04,"equation":"4^2 - 5^1 + 6^3 = 227"},"230":{"difficulty":18.82,"equation":"4^4 - 5^2 - 6^0 = 230"},"231":{"difficulty":17.29,"equation":"4^2 - 5^0 + 6^3 = 231"},"232":{"difficulty":17.55,"equation":"4^2 * 5^0 + 6^3 = 232"},"233":{"difficulty":17.81,"equation":"4^2 + 5^0 + 6^3 = 233"},"234":{"difficulty":30.05,"equation":"4^3 - 5^2 * 6^1 = 234"},"236":{"difficulty":19.36,"equation":"4^1 * 5^1 + 6^3 = 236"},"237":{"difficulty":19.26,"equation":"4^4 - 5^2 + 6^1 = 237"},"239":{"difficulty":99.02,"equation":"4^1 * 6^3 - 5^4 = 239"},"240":{"difficulty":18.95,"equation":"5^2 - 4^0 + 6^3 = 240"},"241":{"difficulty":19.04,"equation":"4^0 * 5^2 + 6^3 = 241"},"242":{"difficulty":19.13,"equation":"4^0 + 5^2 + 6^3 = 242"},"244":{"difficulty":26.85,"equation":"5^1 * 6^2 + 4^3 = 244"},"245":{"difficulty":16.28,"equation":"4^4 - 5^1 - 6^1 = 245"},"246":{"difficulty":31.49,"equation":"4^2 + 5^2 * 6^1 = 246"},"247":{"difficulty":99.03,"equation":"6^4 - 4^5 - 5^2 = 247"},"248":{"difficulty":99.03,"equation":"4^5 + 6^3 / 5^1 = 248"},"249":{"difficulty":14.71,"equation":"4^4 - 5^0 - 6^1 = 249"},"250":{"difficulty":14.52,"equation":"4^4 * 5^0 - 6^1 = 250"},"251":{"difficulty":14.32,"equation":"4^4 + 5^0 - 6^1 = 251"},"252":{"difficulty":14.13,"equation":"4^4 - 5^1 + 6^0 = 252"},"254":{"difficulty":12.95,"equation":"4^4 - 5^0 - 6^0 = 254"},"255":{"difficulty":12.75,"equation":"4^4 - 5^0 * 6^0 = 255"},"256":{"difficulty":12.56,"equation":"4^4 + 5^0 - 6^0 = 256"},"257":{"difficulty":12.81,"equation":"4^4 + 5^0 * 6^0 = 257"},"258":{"difficulty":13.07,"equation":"4^4 + 5^0 + 6^0 = 258"},"259":{"difficulty":35.91,"equation":"4^3 * 6^1 - 5^3 = 259"},"260":{"difficulty":14.38,"equation":"4^4 + 5^1 - 6^0 = 260"},"261":{"difficulty":14.64,"equation":"4^4 - 5^0 + 6^1 = 261"},"262":{"difficulty":14.89,"equation":"4^4 * 5^0 + 6^1 = 262"},"263":{"difficulty":15.15,"equation":"4^4 + 5^0 + 6^1 = 263"},"267":{"difficulty":16.97,"equation":"4^4 + 5^1 + 6^1 = 267"},"269":{"difficulty":36.08,"equation":"4^1 * 6^2 + 5^3 = 269"},"270":{"difficulty":24.79,"equation":"6^3 / 4^1 * 5^1 = 270"},"271":{"difficulty":99.03,"equation":"6^4 - 4^5 - 5^0 = 271"},"272":{"difficulty":99.03,"equation":"4^3 + 6^4 / 5^1 = 272"},"273":{"difficulty":99.03,"equation":"5^0 - 4^5 + 6^4 = 273"},"275":{"difficulty":20.45,"equation":"4^4 + 5^2 - 6^1 = 275"},"277":{"difficulty":28.03,"equation":"5^3 - 4^3 + 6^3 = 277"},"279":{"difficulty":26.32,"equation":"4^3 - 5^0 + 6^3 = 279"},"280":{"difficulty":20.94,"equation":"4^4 + 5^2 - 6^0 = 280"},"281":{"difficulty":21.2,"equation":"4^4 + 5^2 * 6^0 = 281"},"282":{"difficulty":21.45,"equation":"4^4 + 5^2 + 6^0 = 282"},"284":{"difficulty":25.69,"equation":"4^3 * 5^1 - 6^2 = 284"},"285":{"difficulty":28.65,"equation":"4^3 + 5^1 + 6^3 = 285"},"286":{"difficulty":23.51,"equation":"5^1 * 6^1 + 4^4 = 286"},"287":{"difficulty":23.52,"equation":"4^4 - 5^1 + 6^2 = 287"},"290":{"difficulty":51.46,"equation":"4^3 - 6^1 * 5^1 = 290"},"291":{"difficulty":23.75,"equation":"4^4 - 5^0 + 6^2 = 291"},"292":{"difficulty":24.01,"equation":"4^4 * 5^0 + 6^2 = 292"},"293":{"difficulty":24.26,"equation":"4^4 + 5^0 + 6^2 = 293"},"296":{"difficulty":33.13,"equation":"4^2 * 5^1 + 6^3 = 296"},"297":{"difficulty":26.08,"equation":"4^4 + 5^1 + 6^2 = 297"},"299":{"difficulty":99.03,"equation":"6^4 / 4^1 - 5^2 = 299"},"304":{"difficulty":52.25,"equation":"5^2 - 6^1 * 4^2 = 304"},"305":{"difficulty":35.18,"equation":"4^3 + 5^2 + 6^3 = 305"},"311":{"difficulty":99.22,"equation":"6^5 - 4^0 / 5^2 = 311"},"314":{"difficulty":23.34,"equation":"4^3 * 5^1 - 6^1 = 314"},"315":{"difficulty":55.37,"equation":"4^3 - 6^0 * 5^1 = 315"},"316":{"difficulty":37.97,"equation":"4^1 * 5^2 + 6^3 = 316"},"317":{"difficulty":32.6,"equation":"4^4 + 5^2 + 6^2 = 317"},"319":{"difficulty":22.39,"equation":"4^3 * 5^1 - 6^0 = 319"},"320":{"difficulty":20.69,"equation":"4^3 * 5^1 * 6^0 = 320"},"321":{"difficulty":22.62,"equation":"4^3 * 5^1 + 6^0 = 321"},"323":{"difficulty":99.03,"equation":"6^4 / 4^1 - 5^0 = 323"},"324":{"difficulty":43.89,"equation":"4^1 + 5^1 * 6^2 = 324"},"325":{"difficulty":23.63,"equation":"6^0 + 4^3 * 5^1 = 325"},"326":{"difficulty":24.68,"equation":"4^3 * 5^1 + 6^1 = 326"},"329":{"difficulty":99.03,"equation":"6^4 / 4^1 + 5^1 = 329"},"331":{"difficulty":99.1,"equation":"4^2 * 6^3 - 5^5 = 331"},"333":{"difficulty":67.94,"equation":"5^4 - 4^4 - 6^2 = 333"},"337":{"difficulty":41.88,"equation":"5^3 - 4^1 + 6^3 = 337"},"340":{"difficulty":41.85,"equation":"5^3 - 4^0 + 6^3 = 340"},"341":{"difficulty":42.1,"equation":"4^0 * 5^3 + 6^3 = 341"},"342":{"difficulty":42.36,"equation":"4^0 + 5^3 + 6^3 = 342"},"345":{"difficulty":39.71,"equation":"4^4 + 5^3 - 6^2 = 345"},"347":{"difficulty":40.21,"equation":"4^4 - 5^3 + 6^3 = 347"},"349":{"difficulty":99.03,"equation":"6^4 / 4^1 + 5^2 = 349"},"350":{"difficulty":30.76,"equation":"6^1 + 4^3 * 5^1 = 350"},"352":{"difficulty":99.22,"equation":"4^5 + 6^5 / 5^2 = 352"},"353":{"difficulty":99.03,"equation":"4^5 + 5^4 - 6^4 = 353"},"354":{"difficulty":67.72,"equation":"4^3 - 5^1 * 6^1 = 354"},"356":{"difficulty":33.71,"equation":"4^3 * 5^1 + 6^2 = 356"},"357":{"difficulty":48.37,"equation":"4^2 + 5^3 + 6^3 = 357"},"359":{"difficulty":32.82,"equation":"4^3 * 6^1 - 5^2 = 359"},"361":{"difficulty":99.22,"equation":"6^5 / 4^2 - 5^3 = 361"},"363":{"difficulty":65.53,"equation":"5^4 - 4^4 - 6^1 = 363"},"364":{"difficulty":38.47,"equation":"4^2 * 5^2 - 6^2 = 364"},"366":{"difficulty":32.58,"equation":"5^3 - 4^3 * 6^1 = 366"},"368":{"difficulty":64.57,"equation":"5^4 - 4^4 - 6^0 = 368"},"369":{"difficulty":64.54,"equation":"5^4 - 4^4 * 6^0 = 369"},"370":{"difficulty":64.5,"equation":"5^4 - 4^4 + 6^0 = 370"},"375":{"difficulty":45.85,"equation":"4^4 + 5^3 - 6^1 = 375"},"378":{"difficulty":71.32,"equation":"4^3 - 5^0 * 6^1 = 378"},"379":{"difficulty":30.72,"equation":"4^3 * 6^1 - 5^1 = 379"},"380":{"difficulty":46.32,"equation":"4^4 + 5^3 - 6^0 = 380"},"381":{"difficulty":46.57,"equation":"4^4 + 5^3 * 6^0 = 381"},"382":{"difficulty":46.82,"equation":"4^4 + 5^3 + 6^0 = 382"},"383":{"difficulty":29.79,"equation":"4^3 * 6^1 - 5^0 = 383"},"384":{"difficulty":27.84,"equation":"4^3 * 6^1 * 5^0 = 384"},"385":{"difficulty":30.01,"equation":"4^3 * 6^1 + 5^0 = 385"},"387":{"difficulty":48.87,"equation":"4^4 + 5^3 + 6^1 = 387"},"389":{"difficulty":31.81,"equation":"4^3 * 6^1 + 5^1 = 389"},"390":{"difficulty":31.26,"equation":"5^0 + 4^3 * 6^1 = 390"},"393":{"difficulty":65.95,"equation":"5^4 - 4^2 - 6^3 = 393"},"394":{"difficulty":36.03,"equation":"4^2 * 5^2 - 6^1 = 394"},"396":{"difficulty":63.51,"equation":"4^2 - 5^1 * 6^2 = 396"},"397":{"difficulty":99.03,"equation":"5^3 - 4^5 + 6^4 = 397"},"398":{"difficulty":99.02,"equation":"4^5 - 5^4 - 6^0 = 398"},"399":{"difficulty":35.06,"equation":"4^2 * 5^2 - 6^0 = 399"},"400":{"difficulty":31.03,"equation":"4^2 * 5^2 * 6^0 = 400"},"401":{"difficulty":35.28,"equation":"4^2 * 5^2 + 6^0 = 401"},"405":{"difficulty":60.46,"equation":"4^3 + 5^3 + 6^3 = 405"},"406":{"difficulty":37.33,"equation":"4^2 * 5^2 + 6^1 = 406"},"408":{"difficulty":63.21,"equation":"5^4 - 4^0 - 6^3 = 408"},"409":{"difficulty":38.26,"equation":"4^3 * 6^1 + 5^2 = 409"},"410":{"difficulty":63.14,"equation":"4^0 + 5^4 - 6^3 = 410"},"413":{"difficulty":63.83,"equation":"4^1 + 5^4 - 6^3 = 413"},"414":{"difficulty":38.08,"equation":"5^1 + 4^3 * 6^1 = 414"},"415":{"difficulty":99.03,"equation":"6^4 - 4^4 - 5^4 = 415"},"416":{"difficulty":39.04,"equation":"6^0 + 5^2 * 4^2 = 416"},"417":{"difficulty":57.84,"equation":"4^4 + 5^3 + 6^2 = 417"},"425":{"difficulty":41.3,"equation":"6^0 + 4^2 * 5^2 = 425"},"432":{"difficulty":62.78,"equation":"4^0 + 5^0 * 6^3 = 432"},"435":{"difficulty":99.02,"equation":"4^5 - 5^4 + 6^2 = 435"},"436":{"difficulty":46.27,"equation":"4^2 * 5^2 + 6^2 = 436"},"447":{"difficulty":64.26,"equation":"4^4 - 5^2 + 6^3 = 447"},"448":{"difficulty":44.55,"equation":"5^0 + 6^1 * 4^3 = 448"},"449":{"difficulty":99.03,"equation":"6^4 / 4^1 + 5^3 = 449"},"451":{"difficulty":59.09,"equation":"4^2 * 6^2 - 5^3 = 451"},"461":{"difficulty":99.22,"equation":"6^5 / 4^2 - 5^2 = 461"},"464":{"difficulty":41.48,"equation":"4^1 * 5^3 - 6^2 = 464"},"467":{"difficulty":64.49,"equation":"4^4 - 5^1 + 6^3 = 467"},"471":{"difficulty":64.03,"equation":"4^4 - 5^0 + 6^3 = 471"},"472":{"difficulty":64.11,"equation":"4^4 * 5^0 + 6^3 = 472"},"473":{"difficulty":57.69,"equation":"4^3 + 5^4 - 6^3 = 473"},"476":{"difficulty":83.63,"equation":"5^3 - 6^1 * 4^1 = 476"},"477":{"difficulty":65.32,"equation":"4^4 + 5^1 + 6^3 = 477"},"480":{"difficulty":88.28,"equation":"4^2 * 6^1 * 5^1 = 480"},"481":{"difficulty":99.22,"equation":"6^5 / 4^2 - 5^1 = 481"},"485":{"difficulty":99.22,"equation":"6^5 / 4^2 - 5^0 = 485"},"486":{"difficulty":99.22,"equation":"5^0 * 6^5 / 4^2 = 486"},"487":{"difficulty":99.22,"equation":"6^5 / 4^2 + 5^0 = 487"},"491":{"difficulty":99.22,"equation":"6^5 / 4^2 + 5^1 = 491"},"494":{"difficulty":33.95,"equation":"4^1 * 5^3 - 6^1 = 494"},"496":{"difficulty":50.56,"equation":"6^1 + 5^2 * 4^2 = 496"},"497":{"difficulty":68.39,"equation":"4^4 + 5^2 + 6^3 = 497"},"499":{"difficulty":32.14,"equation":"4^1 * 5^3 - 6^0 = 499"},"500":{"difficulty":30.52,"equation":"4^1 * 5^3 * 6^0 = 500"},"501":{"difficulty":32.02,"equation":"4^1 * 5^3 + 6^0 = 501"},"504":{"difficulty":32.27,"equation":"6^0 + 5^3 * 4^1 = 504"},"506":{"difficulty":33.22,"equation":"4^1 * 5^3 + 6^1 = 506"},"509":{"difficulty":51.8,"equation":"4^3 * 6^1 + 5^3 = 509"},"511":{"difficulty":99.22,"equation":"6^5 / 4^2 + 5^2 = 511"},"512":{"difficulty":65.17,"equation":"5^0 + 6^0 * 4^4 = 512"},"521":{"difficulty":99.08,"equation":"4^0 + 5^5 / 6^1 = 521"},"524":{"difficulty":34.69,"equation":"6^1 + 5^3 * 4^1 = 524"},"525":{"difficulty":47.09,"equation":"5^4 - 4^3 - 6^2 = 525"},"534":{"difficulty":53.83,"equation":"5^2 + 4^3 * 6^1 = 534"},"536":{"difficulty":37.09,"equation":"4^1 * 5^3 + 6^2 = 536"},"540":{"difficulty":99.02,"equation":"4^2 - 5^0 * 6^2 = 540"},"550":{"difficulty":54.95,"equation":"6^1 + 4^2 * 5^2 = 550"},"551":{"difficulty":38.71,"equation":"4^2 * 6^2 - 5^2 = 551"},"555":{"difficulty":39.53,"equation":"5^4 - 4^3 - 6^1 = 555"},"560":{"difficulty":37.71,"equation":"5^4 - 4^3 - 6^0 = 560"},"561":{"difficulty":37.5,"equation":"5^4 - 4^3 * 6^0 = 561"},"562":{"difficulty":37.3,"equation":"5^4 - 4^3 + 6^0 = 562"},"567":{"difficulty":37.06,"equation":"5^4 - 4^3 + 6^1 = 567"},"571":{"difficulty":33.18,"equation":"4^2 * 6^2 - 5^1 = 571"},"573":{"difficulty":37.26,"equation":"5^4 - 4^2 - 6^2 = 573"},"575":{"difficulty":31.57,"equation":"4^2 * 6^2 - 5^0 = 575"},"576":{"difficulty":27.36,"equation":"4^2 * 6^2 * 5^0 = 576"},"577":{"difficulty":31.44,"equation":"4^2 * 6^2 + 5^0 = 577"},"581":{"difficulty":32.56,"equation":"4^2 * 6^2 + 5^1 = 581"},"585":{"difficulty":33.37,"equation":"5^4 - 4^1 - 6^2 = 585"},"588":{"difficulty":31.96,"equation":"5^4 - 4^0 - 6^2 = 588"},"589":{"difficulty":31.75,"equation":"4^0 * 5^4 - 6^2 = 589"},"590":{"difficulty":31.55,"equation":"4^0 + 5^4 - 6^2 = 590"},"592":{"difficulty":32.64,"equation":"5^0 + 6^2 * 4^2 = 592"},"593":{"difficulty":31.72,"equation":"4^1 + 5^4 - 6^2 = 593"},"597":{"difficulty":32.33,"equation":"5^4 - 4^3 + 6^2 = 597"},"600":{"difficulty":99.02,"equation":"4^1 * 5^2 * 6^1 = 600"},"601":{"difficulty":35.59,"equation":"4^2 * 6^2 + 5^2 = 601"},"603":{"difficulty":29.67,"equation":"5^4 - 4^2 - 6^1 = 603"},"604":{"difficulty":100,"equation":"6^6 / 4^3 - 5^3 = 604"},"605":{"difficulty":30.68,"equation":"4^2 + 5^4 - 6^2 = 605"},"607":{"difficulty":99.03,"equation":"6^4 - 4^3 - 5^4 = 607"},"608":{"difficulty":27.84,"equation":"5^4 - 4^2 - 6^0 = 608"},"609":{"difficulty":27.64,"equation":"5^4 - 4^2 * 6^0 = 609"},"610":{"difficulty":27.43,"equation":"5^4 - 4^2 + 6^0 = 610"},"611":{"difficulty":99.21,"equation":"6^5 / 4^2 + 5^3 = 611"},"612":{"difficulty":34.24,"equation":"5^0 + 4^2 * 6^2 = 612"},"615":{"difficulty":25.77,"equation":"5^4 - 4^1 - 6^1 = 615"},"616":{"difficulty":61.68,"equation":"4^2 * 5^2 + 6^3 = 616"},"618":{"difficulty":24.35,"equation":"5^4 - 4^0 - 6^1 = 618"},"619":{"difficulty":24.15,"equation":"4^0 * 5^4 - 6^1 = 619"},"620":{"difficulty":23.94,"equation":"4^0 + 5^4 - 6^1 = 620"},"621":{"difficulty":23.74,"equation":"5^4 - 4^1 * 6^0 = 621"},"622":{"difficulty":23.53,"equation":"5^4 - 4^1 + 6^0 = 622"},"623":{"difficulty":22.53,"equation":"5^4 - 4^0 - 6^0 = 623"},"624":{"difficulty":22.32,"equation":"4^0 * 5^4 - 6^0 = 624"},"625":{"difficulty":22.12,"equation":"4^0 + 5^4 - 6^0 = 625"},"626":{"difficulty":22.36,"equation":"4^0 + 5^4 * 6^0 = 626"},"627":{"difficulty":22.61,"equation":"4^0 + 5^4 + 6^0 = 627"},"628":{"difficulty":23.65,"equation":"4^1 + 5^4 - 6^0 = 628"},"629":{"difficulty":23.9,"equation":"4^1 + 5^4 * 6^0 = 629"},"630":{"difficulty":24.14,"equation":"4^1 + 5^4 + 6^0 = 630"},"631":{"difficulty":24.39,"equation":"4^0 * 5^4 + 6^1 = 631"},"632":{"difficulty":24.63,"equation":"4^0 + 5^4 + 6^1 = 632"},"634":{"difficulty":27.35,"equation":"6^2 / 4^1 + 5^4 = 634"},"635":{"difficulty":26.17,"equation":"4^1 + 5^4 + 6^1 = 635"},"640":{"difficulty":28.03,"equation":"4^2 + 5^4 - 6^0 = 640"},"641":{"difficulty":28.28,"equation":"4^2 + 5^4 * 6^0 = 641"},"642":{"difficulty":28.52,"equation":"4^2 + 5^4 + 6^0 = 642"},"644":{"difficulty":48.92,"equation":"6^2 + 5^3 * 4^1 = 644"},"645":{"difficulty":31.48,"equation":"5^4 - 4^2 + 6^2 = 645"},"647":{"difficulty":30.55,"equation":"4^2 + 5^4 + 6^1 = 647"},"648":{"difficulty":86.35,"equation":"4^1 - 5^0 * 6^3 = 648"},"649":{"difficulty":31.02,"equation":"4^1 * 6^1 + 5^4 = 649"},"653":{"difficulty":33.45,"equation":"4^3 + 5^4 - 6^2 = 653"},"654":{"difficulty":99.02,"equation":"5^3 - 4^2 * 6^1 = 654"},"655":{"difficulty":99.02,"equation":"6^4 - 4^2 - 5^4 = 655"},"656":{"difficulty":43.7,"equation":"5^1 + 6^2 * 4^2 = 656"},"657":{"difficulty":33,"equation":"5^4 - 4^1 + 6^2 = 657"},"660":{"difficulty":32.95,"equation":"5^4 - 4^0 + 6^2 = 660"},"661":{"difficulty":33.19,"equation":"4^0 * 5^4 + 6^2 = 661"},"662":{"difficulty":33.44,"equation":"4^0 + 5^4 + 6^2 = 662"},"665":{"difficulty":34.97,"equation":"4^1 + 5^4 + 6^2 = 665"},"667":{"difficulty":99.02,"equation":"6^4 - 4^1 - 5^4 = 667"},"670":{"difficulty":99.02,"equation":"6^4 - 4^0 - 5^4 = 670"},"671":{"difficulty":99.02,"equation":"4^0 * 6^4 - 5^4 = 671"},"672":{"difficulty":99.02,"equation":"4^0 - 5^4 + 6^4 = 672"},"675":{"difficulty":99.02,"equation":"4^1 - 5^4 + 6^4 = 675"},"677":{"difficulty":39.34,"equation":"4^2 + 5^4 + 6^2 = 677"},"679":{"difficulty":38.41,"equation":"6^3 / 4^1 + 5^4 = 679"},"683":{"difficulty":39.39,"equation":"4^3 + 5^4 - 6^1 = 683"},"686":{"difficulty":42.62,"equation":"5^3 * 6^1 - 4^3 = 686"},"687":{"difficulty":99.02,"equation":"4^2 - 5^4 + 6^4 = 687"},"688":{"difficulty":39.82,"equation":"4^3 + 5^4 - 6^0 = 688"},"689":{"difficulty":40.07,"equation":"4^3 + 5^4 * 6^0 = 689"},"690":{"difficulty":40.31,"equation":"4^3 + 5^4 + 6^0 = 690"},"695":{"difficulty":42.33,"equation":"4^3 + 5^4 + 6^1 = 695"},"700":{"difficulty":68.74,"equation":"4^3 - 6^2 * 5^2 = 700"},"701":{"difficulty":56.17,"equation":"4^2 * 6^2 + 5^3 = 701"},"704":{"difficulty":79.12,"equation":"5^1 + 6^1 * 4^3 = 704"},"706":{"difficulty":99.02,"equation":"6^4 / 4^2 + 5^4 = 706"},"716":{"difficulty":66.58,"equation":"4^1 * 5^3 + 6^3 = 716"},"720":{"difficulty":99.02,"equation":"4^1 * 6^2 * 5^1 = 720"},"721":{"difficulty":50.62,"equation":"4^2 * 6^1 + 5^4 = 721"},"724":{"difficulty":100,"equation":"6^6 / 4^3 - 5^1 = 724"},"725":{"difficulty":51.11,"equation":"4^3 + 5^4 + 6^2 = 725"},"726":{"difficulty":99.02,"equation":"5^3 - 4^1 * 6^1 = 726"},"728":{"difficulty":100,"equation":"6^6 / 4^3 - 5^0 = 728"},"729":{"difficulty":100,"equation":"5^0 / 4^3 * 6^6 = 729"},"730":{"difficulty":100,"equation":"6^6 / 4^3 + 5^0 = 730"},"734":{"difficulty":40.66,"equation":"5^3 * 6^1 - 4^2 = 734"},"735":{"difficulty":99.02,"equation":"4^3 - 5^4 + 6^4 = 735"},"739":{"difficulty":56.36,"equation":"4^1 * 6^3 - 5^3 = 739"},"744":{"difficulty":99.02,"equation":"5^3 - 4^0 * 6^1 = 744"},"746":{"difficulty":38.74,"equation":"5^3 * 6^1 - 4^1 = 746"},"749":{"difficulty":37.82,"equation":"5^3 * 6^1 - 4^0 = 749"},"750":{"difficulty":35.86,"equation":"5^3 * 6^1 * 4^0 = 750"},"751":{"difficulty":38.02,"equation":"5^3 * 6^1 + 4^0 = 751"},"754":{"difficulty":39.55,"equation":"5^3 * 6^1 + 4^1 = 754"},"756":{"difficulty":39.25,"equation":"4^0 + 5^3 * 6^1 = 756"},"760":{"difficulty":99.02,"equation":"6^3 - 4^3 * 5^1 = 760"},"764":{"difficulty":99.02,"equation":"6^3 - 5^2 * 4^1 = 764"},"766":{"difficulty":43.91,"equation":"5^3 * 6^1 + 4^2 = 766"},"769":{"difficulty":61.85,"equation":"4^1 * 6^2 + 5^4 = 769"},"774":{"difficulty":44.44,"equation":"4^1 + 5^3 * 6^1 = 774"},"777":{"difficulty":63.82,"equation":"5^4 - 4^3 + 6^3 = 777"},"781":{"difficulty":99.08,"equation":"5^5 - 6^0 / 4^1 = 781"},"783":{"difficulty":77.58,"equation":"4^5 - 5^2 - 6^3 = 783"},"786":{"difficulty":48.8,"equation":"4^4 - 5^3 * 6^1 = 786"},"800":{"difficulty":99.03,"equation":"6^2 - 4^1 * 5^2 = 800"},"803":{"difficulty":75.31,"equation":"4^5 - 5^1 - 6^3 = 803"},"805":{"difficulty":99.08,"equation":"5^5 - 4^5 - 6^4 = 805"},"807":{"difficulty":74.35,"equation":"4^5 - 5^0 - 6^3 = 807"},"808":{"difficulty":74.31,"equation":"4^5 * 5^0 - 6^3 = 808"},"809":{"difficulty":74.27,"equation":"4^5 + 5^0 - 6^3 = 809"},"813":{"difficulty":74.89,"equation":"4^5 + 5^1 - 6^3 = 813"},"814":{"difficulty":55.62,"equation":"5^3 * 6^1 + 4^3 = 814"},"824":{"difficulty":84.16,"equation":"5^1 * 6^3 - 4^4 = 824"},"825":{"difficulty":75.44,"equation":"5^4 - 4^2 + 6^3 = 825"},"833":{"difficulty":74.06,"equation":"4^5 + 5^2 - 6^3 = 833"},"836":{"difficulty":61.19,"equation":"5^2 * 6^2 - 4^3 = 836"},"837":{"difficulty":74.93,"equation":"5^4 - 4^1 + 6^3 = 837"},"839":{"difficulty":49.78,"equation":"4^1 * 6^3 - 5^2 = 839"},"840":{"difficulty":74.37,"equation":"5^4 - 4^0 + 6^3 = 840"},"841":{"difficulty":74.45,"equation":"4^0 * 5^4 + 6^3 = 841"},"842":{"difficulty":74.52,"equation":"4^0 + 5^4 + 6^3 = 842"},"844":{"difficulty":99.03,"equation":"6^3 - 5^1 * 4^1 = 844"},"845":{"difficulty":75.55,"equation":"4^1 + 5^4 + 6^3 = 845"},"846":{"difficulty":59.83,"equation":"4^2 + 5^3 * 6^1 = 846"},"854":{"difficulty":100,"equation":"6^6 / 4^3 + 5^3 = 854"},"857":{"difficulty":77.9,"equation":"4^2 + 5^4 + 6^3 = 857"},"859":{"difficulty":44.17,"equation":"4^1 * 6^3 - 5^1 = 859"},"860":{"difficulty":99.03,"equation":"6^3 - 5^0 * 4^1 = 860"},"863":{"difficulty":42.54,"equation":"4^1 * 6^3 - 5^0 = 863"},"864":{"difficulty":40.91,"equation":"4^1 * 6^3 * 5^0 = 864"},"865":{"difficulty":42.4,"equation":"4^1 * 6^3 + 5^0 = 865"},"868":{"difficulty":42.63,"equation":"5^0 + 6^3 * 4^1 = 868"},"869":{"difficulty":43.5,"equation":"4^1 * 6^3 + 5^1 = 869"},"875":{"difficulty":59.83,"equation":"4^0 + 6^1 * 5^3 = 875"},"880":{"difficulty":77.43,"equation":"4^4 + 5^4 - 6^0 = 880"},"881":{"difficulty":77.51,"equation":"4^4 + 5^4 * 6^0 = 881"},"882":{"difficulty":77.59,"equation":"4^4 + 5^4 + 6^0 = 882"},"884":{"difficulty":44.65,"equation":"5^1 + 6^3 * 4^1 = 884"},"887":{"difficulty":78.76,"equation":"4^4 + 5^4 + 6^1 = 887"},"889":{"difficulty":46.46,"equation":"4^1 * 6^3 + 5^2 = 889"},"893":{"difficulty":60.09,"equation":"4^5 - 5^3 - 6^1 = 893"},"896":{"difficulty":47.21,"equation":"5^2 * 6^2 - 4^1 = 896"},"897":{"difficulty":99.02,"equation":"5^4 - 4^5 + 6^4 = 897"},"898":{"difficulty":58.24,"equation":"4^5 - 5^3 - 6^0 = 898"},"899":{"difficulty":45.79,"equation":"5^2 * 6^2 - 4^0 = 899"},"900":{"difficulty":39.99,"equation":"5^2 * 6^2 * 4^0 = 900"},"901":{"difficulty":45.65,"equation":"5^2 * 6^2 + 4^0 = 901"},"904":{"difficulty":46.67,"equation":"5^2 * 6^2 + 4^1 = 904"},"905":{"difficulty":57.57,"equation":"4^5 - 5^3 + 6^1 = 905"},"911":{"difficulty":99.03,"equation":"4^4 * 6^1 - 5^4 = 911"},"915":{"difficulty":99.02,"equation":"6^4 - 4^4 - 5^3 = 915"},"916":{"difficulty":49.02,"equation":"5^2 * 6^2 + 4^2 = 916"},"917":{"difficulty":82.48,"equation":"4^4 + 5^4 + 6^2 = 917"},"925":{"difficulty":47.48,"equation":"4^0 + 6^2 * 5^2 = 925"},"927":{"difficulty":99.02,"equation":"4^4 - 5^4 + 6^4 = 927"},"933":{"difficulty":53.13,"equation":"4^5 + 5^3 - 6^3 = 933"},"935":{"difficulty":52.71,"equation":"4^5 - 5^3 + 6^2 = 935"},"936":{"difficulty":48.31,"equation":"4^0 + 5^2 * 6^2 = 936"},"949":{"difficulty":87.45,"equation":"6^4 / 4^1 + 5^4 = 949"},"963":{"difficulty":46.83,"equation":"4^5 - 5^2 - 6^2 = 963"},"964":{"difficulty":52.16,"equation":"5^2 + 6^3 * 4^1 = 964"},"976":{"difficulty":99.02,"equation":"5^2 + 6^2 * 4^2 = 976"},"983":{"difficulty":41.2,"equation":"4^5 - 5^1 - 6^2 = 983"},"987":{"difficulty":39.56,"equation":"4^5 - 5^0 - 6^2 = 987"},"988":{"difficulty":39.35,"equation":"4^5 * 5^0 - 6^2 = 988"},"989":{"difficulty":39.14,"equation":"4^5 + 5^0 - 6^2 = 989"},"993":{"difficulty":39.1,"equation":"4^5 + 5^1 - 6^2 = 993"},"998":{"difficulty":37.25,"equation":"4^5 - 5^2 - 6^0 = 998"},"999":{"difficulty":37.04,"equation":"4^5 - 5^2 * 6^0 = 999"}}}